Workbook

Sheet Start Here
A1: Business Budget & Expense Tracker
A2: Plan the year, log what happens, and always know where you stand vs. budget.
B4: Welcome!
B5: Built for small businesses, startups, and teams: set a month-by-month budget per category, log expenses and revenue as they happen, and the dashboard reports actuals vs. budget with variance — monthly, quarterly, and by category.
B8: 1. Plan the year on Budget Plan
C9: One row per category, one column per month. Budgets can differ by month — seasonal is fine. Rename categories to match your business.
B11: 2. Log every expense
C12: On Expenses: date, vendor, category (dropdown), description, amount.
B14: 3. Log revenue
C15: On Revenue: date, client or source, amount. Keeps the dashboard honest about the whole picture.
B17: 4. Read the Dashboard
C18: Budget vs. actual with variance by month, quarter, and category — plus revenue and net. Overruns show in red.
B20: Color guide
C21: Light yellow cells = yours to fill in or change
C22: Grey / white cells = calculated automatically — no need to touch them
B24: Note: the file includes example data so you can see how everything works — delete it and add your own.
B25: Works in Microsoft Excel (2016 or newer) and Google Sheets (upload to Drive, then Open with Google Sheets).
B26: Formulas are protected so you can't break anything by accident — every cell meant for typing is unlocked. To change anything else: Review → Unprotect Sheet (no password).
B27: This is a planning aid, not accounting or tax advice.

Sheet Budget Plan
A1: Budget Plan
A2: Month-by-month budget per category. Yellow cells are yours — seasonal budgets welcome.
A5: ANNUAL BUDGET BY CATEGORY
A7: Category | B7: Jan | C7: Feb | D7: Mar | E7: Apr | F7: May | G7: Jun | H7: Jul | I7: Aug | J7: Sep | K7: Oct | L7: Nov | M7: Dec | N7: Annual
A8: Payroll & contractors | B8: 6500 | C8: 6500 | D8: 6500 | E8: 6500 | F8: 6500 | G8: 6500 | H8: 6500 | I8: 6500 | J8: 6500 | K8: 6500 | L8: 6500 | M8: 6500 | N8: =IF($A8="","",SUM(B8:M8)) -> 78000
A9: Rent & utilities | B9: 1200 | C9: 1200 | D9: 1200 | E9: 1200 | F9: 1200 | G9: 1200 | H9: 1200 | I9: 1200 | J9: 1200 | K9: 1200 | L9: 1200 | M9: 1200 | N9: =IF($A9="","",SUM(B9:M9)) -> 14400
A10: Software & subscriptions | B10: 300 | C10: 300 | D10: 300 | E10: 300 | F10: 300 | G10: 300 | H10: 300 | I10: 300 | J10: 300 | K10: 300 | L10: 300 | M10: 300 | N10: =IF($A10="","",SUM(B10:M10)) -> 3600
A11: Marketing & ads | B11: 600 | C11: 600 | D11: 600 | E11: 600 | F11: 600 | G11: 600 | H11: 600 | I11: 600 | J11: 600 | K11: 600 | L11: 600 | M11: 600 | N11: =IF($A11="","",SUM(B11:M11)) -> 7200
A12: Travel | B12: 400 | C12: 400 | D12: 400 | E12: 400 | F12: 400 | G12: 400 | H12: 400 | I12: 400 | J12: 400 | K12: 400 | L12: 400 | M12: 400 | N12: =IF($A12="","",SUM(B12:M12)) -> 4800
A13: Equipment | B13: 250 | C13: 250 | D13: 250 | E13: 250 | F13: 250 | G13: 250 | H13: 250 | I13: 250 | J13: 250 | K13: 250 | L13: 250 | M13: 250 | N13: =IF($A13="","",SUM(B13:M13)) -> 3000
A14: Professional services | B14: 350 | C14: 350 | D14: 350 | E14: 350 | F14: 350 | G14: 350 | H14: 350 | I14: 350 | J14: 350 | K14: 350 | L14: 350 | M14: 350 | N14: =IF($A14="","",SUM(B14:M14)) -> 4200
A15: Insurance | B15: 180 | C15: 180 | D15: 180 | E15: 180 | F15: 180 | G15: 180 | H15: 180 | I15: 180 | J15: 180 | K15: 180 | L15: 180 | M15: 180 | N15: =IF($A15="","",SUM(B15:M15)) -> 2160
A16: Taxes & fees | B16: 250 | C16: 250 | D16: 250 | E16: 250 | F16: 250 | G16: 250 | H16: 250 | I16: 250 | J16: 250 | K16: 250 | L16: 250 | M16: 250 | N16: =IF($A16="","",SUM(B16:M16)) -> 3000
A17: Other | B17: 200 | C17: 200 | D17: 200 | E17: 200 | F17: 200 | G17: 200 | H17: 200 | I17: 200 | J17: 200 | K17: 200 | L17: 200 | M17: 200 | N17: =IF($A17="","",SUM(B17:M17)) -> 2400
N18: =IF($A18="","",SUM(B18:M18))
N19: =IF($A19="","",SUM(B19:M19))
N20: =IF($A20="","",SUM(B20:M20))
N21: =IF($A21="","",SUM(B21:M21))
N22: =IF($A22="","",SUM(B22:M22))
N23: =IF($A23="","",SUM(B23:M23))
A24: Monthly total | B24: =SUM(B8:B23) -> 10230 | C24: =SUM(C8:C23) -> 10230 | D24: =SUM(D8:D23) -> 10230 | E24: =SUM(E8:E23) -> 10230 | F24: =SUM(F8:F23) -> 10230 | G24: =SUM(G8:G23) -> 10230 | H24: =SUM(H8:H23) -> 10230 | I24: =SUM(I8:I23) -> 10230 | ... N24: =SUM(N8:N23) -> 122760

Sheet Expenses
A1: Expenses
A2: One row per expense. The Dashboard reads this table automatically.
A4: Every cell in this table is yours to type in. Pick the Category from the dropdown.
A5: Date | B5: Vendor | C5: Category | D5: Description | E5: Amount
A6: 46204 | B6: Gusto | C6: Payroll & contractors | D6: July payroll | E6: 6500
A7: 46206 | B7: WeWork | C7: Rent & utilities | D7: Office + internet | E7: 1200
A8: 46208 | B8: Adobe / Notion | C8: Software & subscriptions | D8: Monthly seats | E8: 240
A9: 46215 | B9: LinkedIn | C9: Marketing & ads | D9: Lead-gen campaign | E9: 450
A10: 46222 | B10: Delta | C10: Travel | D10: Client visit — flights | E10: 380
A11: 46235 | B11: Gusto | C11: Payroll & contractors | D11: August payroll | E11: 6500
A12: 46237 | B12: WeWork | C12: Rent & utilities | D12: Office + internet | E12: 1200
A13: 46243 | B13: Apple | C13: Equipment | D13: MacBook Air — new hire | E13: 899

Sheet Revenue
A1: Revenue
A2: One row per payment received. Keeps the dashboard honest about the whole picture.
A4: Every cell in this table is yours to type in.
A5: Date | B5: Client / source | C5: Amount | D5: Notes
A6: 46211 | B6: Meridian Co — retainer | C6: 8200
A7: 46225 | B7: Bluestone LLC — project | C7: 3400 | D7: Phase 1
A8: 46240 | B8: Meridian Co — retainer | C8: 8200
A9: 46252 | B9: Harbor Group — workshop | C9: 2750

Sheet Dashboard
A1: Dashboard
A2: Budget vs. actual with variance — monthly, quarterly, and by category.
B4: Year | C4: 2026
B6: REVENUE YTD | D6: EXPENSES YTD | G6: NET | J6: ANNUAL BUDGET LEFT
B7: =SUMIFS(Revenue!$C$6:$C$205,Revenue!$A$6:$A$205,">="&DATE($C$4,1,1),Revenue!$A$6:$A$205,"<"&DATE($C$4+1,1,1)) -> 22550 | D7: =SUMIFS(Expenses!$E$6:$E$405,Expenses!$A$6:$A$405,">="&DATE($C$4,1,1),Expenses!$A$6:$A$405,"<"&DATE($C$4+1,1,1)) -> 17369 | G7: =B7-D7 -> 5181 | J7: ='Budget Plan'!$N$24-D7 -> 105391
B10: Month by month | H10: By category — year to date
A11: # | B11: Month | C11: Budget | D11: Spent | E11: Variance | F11: Revenue | H11: Category | I11: Annual budget | J11: Spent YTD | K11: Left | L11: % used
A12: 1 | B12: January | C12: =INDEX('Budget Plan'!$B$24:$M$24,1,$A12) -> 10230 | D12: =SUMIFS(Expenses!$E$6:$E$405,Expenses!$A$6:$A$405,">="&DATE($C$4,$A12,1),Expenses!$A$6:$A$405,"<"&DATE($C$4,$A12+1,1)) -> 0 | E12: =C12-D12 -> 10230 | F12: =SUMIFS(Revenue!$C$6:$C$205,Revenue!$A$6:$A$205,">="&DATE($C$4,$A12,1),Revenue!$A$6:$A$205,"<"&DATE($C$4,$A12+1,1)) -> 0 | H12: =IF('Budget Plan'!A8="","",'Budget Plan'!A8) -> Payroll & contractors | I12: =IF($H12="","",'Budget Plan'!N8) -> 78000 | J12: =IF($H12="","",SUMIFS(Expenses!$E$6:$E$405,Expenses!$C$6:$C$405,$H12,Expenses!$A$6:$A$405,">="&DATE($C$4,1,1),Expenses!$A$6:$A$405,"<"&DATE($C$4+1,1,1))) -> 13000 | K12: =IF($H12="","",$I12-$J12) -> 65000 | L12: =IF(OR($H12="",$I12=0),"",$J12/$I12) -> 0.16666667
A13: 2 | B13: February | C13: =INDEX('Budget Plan'!$B$24:$M$24,1,$A13) -> 10230 | D13: =SUMIFS(Expenses!$E$6:$E$405,Expenses!$A$6:$A$405,">="&DATE($C$4,$A13,1),Expenses!$A$6:$A$405,"<"&DATE($C$4,$A13+1,1)) -> 0 | E13: =C13-D13 -> 10230 | F13: =SUMIFS(Revenue!$C$6:$C$205,Revenue!$A$6:$A$205,">="&DATE($C$4,$A13,1),Revenue!$A$6:$A$205,"<"&DATE($C$4,$A13+1,1)) -> 0 | H13: =IF('Budget Plan'!A9="","",'Budget Plan'!A9) -> Rent & utilities | I13: =IF($H13="","",'Budget Plan'!N9) -> 14400 | J13: =IF($H13="","",SUMIFS(Expenses!$E$6:$E$405,Expenses!$C$6:$C$405,$H13,Expenses!$A$6:$A$405,">="&DATE($C$4,1,1),Expenses!$A$6:$A$405,"<"&DATE($C$4+1,1,1))) -> 2400 | K13: =IF($H13="","",$I13-$J13) -> 12000 | L13: =IF(OR($H13="",$I13=0),"",$J13/$I13) -> 0.16666667
A14: 3 | B14: March | C14: =INDEX('Budget Plan'!$B$24:$M$24,1,$A14) -> 10230 | D14: =SUMIFS(Expenses!$E$6:$E$405,Expenses!$A$6:$A$405,">="&DATE($C$4,$A14,1),Expenses!$A$6:$A$405,"<"&DATE($C$4,$A14+1,1)) -> 0 | E14: =C14-D14 -> 10230 | F14: =SUMIFS(Revenue!$C$6:$C$205,Revenue!$A$6:$A$205,">="&DATE($C$4,$A14,1),Revenue!$A$6:$A$205,"<"&DATE($C$4,$A14+1,1)) -> 0 | H14: =IF('Budget Plan'!A10="","",'Budget Plan'!A10) -> Software & subscriptions | I14: =IF($H14="","",'Budget Plan'!N10) -> 3600 | J14: =IF($H14="","",SUMIFS(Expenses!$E$6:$E$405,Expenses!$C$6:$C$405,$H14,Expenses!$A$6:$A$405,">="&DATE($C$4,1,1),Expenses!$A$6:$A$405,"<"&DATE($C$4+1,1,1))) -> 240 | K14: =IF($H14="","",$I14-$J14) -> 3360 | L14: =IF(OR($H14="",$I14=0),"",$J14/$I14) -> 0.066666667
A15: 4 | B15: April | C15: =INDEX('Budget Plan'!$B$24:$M$24,1,$A15) -> 10230 | D15: =SUMIFS(Expenses!$E$6:$E$405,Expenses!$A$6:$A$405,">="&DATE($C$4,$A15,1),Expenses!$A$6:$A$405,"<"&DATE($C$4,$A15+1,1)) -> 0 | E15: =C15-D15 -> 10230 | F15: =SUMIFS(Revenue!$C$6:$C$205,Revenue!$A$6:$A$205,">="&DATE($C$4,$A15,1),Revenue!$A$6:$A$205,"<"&DATE($C$4,$A15+1,1)) -> 0 | H15: =IF('Budget Plan'!A11="","",'Budget Plan'!A11) -> Marketing & ads | I15: =IF($H15="","",'Budget Plan'!N11) -> 7200 | J15: =IF($H15="","",SUMIFS(Expenses!$E$6:$E$405,Expenses!$C$6:$C$405,$H15,Expenses!$A$6:$A$405,">="&DATE($C$4,1,1),Expenses!$A$6:$A$405,"<"&DATE($C$4+1,1,1))) -> 450 | K15: =IF($H15="","",$I15-$J15) -> 6750 | L15: =IF(OR($H15="",$I15=0),"",$J15/$I15) -> 0.0625
A16: 5 | B16: May | C16: =INDEX('Budget Plan'!$B$24:$M$24,1,$A16) -> 10230 | D16: =SUMIFS(Expenses!$E$6:$E$405,Expenses!$A$6:$A$405,">="&DATE($C$4,$A16,1),Expenses!$A$6:$A$405,"<"&DATE($C$4,$A16+1,1)) -> 0 | E16: =C16-D16 -> 10230 | F16: =SUMIFS(Revenue!$C$6:$C$205,Revenue!$A$6:$A$205,">="&DATE($C$4,$A16,1),Revenue!$A$6:$A$205,"<"&DATE($C$4,$A16+1,1)) -> 0 | H16: =IF('Budget Plan'!A12="","",'Budget Plan'!A12) -> Travel | I16: =IF($H16="","",'Budget Plan'!N12) -> 4800 | J16: =IF($H16="","",SUMIFS(Expenses!$E$6:$E$405,Expenses!$C$6:$C$405,$H16,Expenses!$A$6:$A$405,">="&DATE($C$4,1,1),Expenses!$A$6:$A$405,"<"&DATE($C$4+1,1,1))) -> 380 | K16: =IF($H16="","",$I16-$J16) -> 4420 | L16: =IF(OR($H16="",$I16=0),"",$J16/$I16) -> 0.079166667
A17: 6 | B17: June | C17: =INDEX('Budget Plan'!$B$24:$M$24,1,$A17) -> 10230 | D17: =SUMIFS(Expenses!$E$6:$E$405,Expenses!$A$6:$A$405,">="&DATE($C$4,$A17,1),Expenses!$A$6:$A$405,"<"&DATE($C$4,$A17+1,1)) -> 0 | E17: =C17-D17 -> 10230 | F17: =SUMIFS(Revenue!$C$6:$C$205,Revenue!$A$6:$A$205,">="&DATE($C$4,$A17,1),Revenue!$A$6:$A$205,"<"&DATE($C$4,$A17+1,1)) -> 0 | H17: =IF('Budget Plan'!A13="","",'Budget Plan'!A13) -> Equipment | I17: =IF($H17="","",'Budget Plan'!N13) -> 3000 | J17: =IF($H17="","",SUMIFS(Expenses!$E$6:$E$405,Expenses!$C$6:$C$405,$H17,Expenses!$A$6:$A$405,">="&DATE($C$4,1,1),Expenses!$A$6:$A$405,"<"&DATE($C$4+1,1,1))) -> 899 | K17: =IF($H17="","",$I17-$J17) -> 2101 | L17: =IF(OR($H17="",$I17=0),"",$J17/$I17) -> 0.29966667
A18: 7 | B18: July | C18: =INDEX('Budget Plan'!$B$24:$M$24,1,$A18) -> 10230 | D18: =SUMIFS(Expenses!$E$6:$E$405,Expenses!$A$6:$A$405,">="&DATE($C$4,$A18,1),Expenses!$A$6:$A$405,"<"&DATE($C$4,$A18+1,1)) -> 8770 | E18: =C18-D18 -> 1460 | F18: =SUMIFS(Revenue!$C$6:$C$205,Revenue!$A$6:$A$205,">="&DATE($C$4,$A18,1),Revenue!$A$6:$A$205,"<"&DATE($C$4,$A18+1,1)) -> 11600 | H18: =IF('Budget Plan'!A14="","",'Budget Plan'!A14) -> Professional services | I18: =IF($H18="","",'Budget Plan'!N14) -> 4200 | J18: =IF($H18="","",SUMIFS(Expenses!$E$6:$E$405,Expenses!$C$6:$C$405,$H18,Expenses!$A$6:$A$405,">="&DATE($C$4,1,1),Expenses!$A$6:$A$405,"<"&DATE($C$4+1,1,1))) -> 0 | K18: =IF($H18="","",$I18-$J18) -> 4200 | L18: =IF(OR($H18="",$I18=0),"",$J18/$I18) -> 0
A19: 8 | B19: August | C19: =INDEX('Budget Plan'!$B$24:$M$24,1,$A19) -> 10230 | D19: =SUMIFS(Expenses!$E$6:$E$405,Expenses!$A$6:$A$405,">="&DATE($C$4,$A19,1),Expenses!$A$6:$A$405,"<"&DATE($C$4,$A19+1,1)) -> 8599 | E19: =C19-D19 -> 1631 | F19: =SUMIFS(Revenue!$C$6:$C$205,Revenue!$A$6:$A$205,">="&DATE($C$4,$A19,1),Revenue!$A$6:$A$205,"<"&DATE($C$4,$A19+1,1)) -> 10950 | H19: =IF('Budget Plan'!A15="","",'Budget Plan'!A15) -> Insurance | I19: =IF($H19="","",'Budget Plan'!N15) -> 2160 | J19: =IF($H19="","",SUMIFS(Expenses!$E$6:$E$405,Expenses!$C$6:$C$405,$H19,Expenses!$A$6:$A$405,">="&DATE($C$4,1,1),Expenses!$A$6:$A$405,"<"&DATE($C$4+1,1,1))) -> 0 | K19: =IF($H19="","",$I19-$J19) -> 2160 | L19: =IF(OR($H19="",$I19=0),"",$J19/$I19) -> 0
A20: 9 | B20: September | C20: =INDEX('Budget Plan'!$B$24:$M$24,1,$A20) -> 10230 | D20: =SUMIFS(Expenses!$E$6:$E$405,Expenses!$A$6:$A$405,">="&DATE($C$4,$A20,1),Expenses!$A$6:$A$405,"<"&DATE($C$4,$A20+1,1)) -> 0 | E20: =C20-D20 -> 10230 | F20: =SUMIFS(Revenue!$C$6:$C$205,Revenue!$A$6:$A$205,">="&DATE($C$4,$A20,1),Revenue!$A$6:$A$205,"<"&DATE($C$4,$A20+1,1)) -> 0 | H20: =IF('Budget Plan'!A16="","",'Budget Plan'!A16) -> Taxes & fees | I20: =IF($H20="","",'Budget Plan'!N16) -> 3000 | J20: =IF($H20="","",SUMIFS(Expenses!$E$6:$E$405,Expenses!$C$6:$C$405,$H20,Expenses!$A$6:$A$405,">="&DATE($C$4,1,1),Expenses!$A$6:$A$405,"<"&DATE($C$4+1,1,1))) -> 0 | K20: =IF($H20="","",$I20-$J20) -> 3000 | L20: =IF(OR($H20="",$I20=0),"",$J20/$I20) -> 0
A21: 10 | B21: October | C21: =INDEX('Budget Plan'!$B$24:$M$24,1,$A21) -> 10230 | D21: =SUMIFS(Expenses!$E$6:$E$405,Expenses!$A$6:$A$405,">="&DATE($C$4,$A21,1),Expenses!$A$6:$A$405,"<"&DATE($C$4,$A21+1,1)) -> 0 | E21: =C21-D21 -> 10230 | F21: =SUMIFS(Revenue!$C$6:$C$205,Revenue!$A$6:$A$205,">="&DATE($C$4,$A21,1),Revenue!$A$6:$A$205,"<"&DATE($C$4,$A21+1,1)) -> 0 | H21: =IF('Budget Plan'!A17="","",'Budget Plan'!A17) -> Other | I21: =IF($H21="","",'Budget Plan'!N17) -> 2400 | J21: =IF($H21="","",SUMIFS(Expenses!$E$6:$E$405,Expenses!$C$6:$C$405,$H21,Expenses!$A$6:$A$405,">="&DATE($C$4,1,1),Expenses!$A$6:$A$405,"<"&DATE($C$4+1,1,1))) -> 0 | K21: =IF($H21="","",$I21-$J21) -> 2400 | L21: =IF(OR($H21="",$I21=0),"",$J21/$I21) -> 0
A22: 11 | B22: November | C22: =INDEX('Budget Plan'!$B$24:$M$24,1,$A22) -> 10230 | D22: =SUMIFS(Expenses!$E$6:$E$405,Expenses!$A$6:$A$405,">="&DATE($C$4,$A22,1),Expenses!$A$6:$A$405,"<"&DATE($C$4,$A22+1,1)) -> 0 | E22: =C22-D22 -> 10230 | F22: =SUMIFS(Revenue!$C$6:$C$205,Revenue!$A$6:$A$205,">="&DATE($C$4,$A22,1),Revenue!$A$6:$A$205,"<"&DATE($C$4,$A22+1,1)) -> 0 | H22: =IF('Budget Plan'!A18="","",'Budget Plan'!A18) | I22: =IF($H22="","",'Budget Plan'!N18) | J22: =IF($H22="","",SUMIFS(Expenses!$E$6:$E$405,Expenses!$C$6:$C$405,$H22,Expenses!$A$6:$A$405,">="&DATE($C$4,1,1),Expenses!$A$6:$A$405,"<"&DATE($C$4+1,1,1))) | K22: =IF($H22="","",$I22-$J22) | L22: =IF(OR($H22="",$I22=0),"",$J22/$I22)
A23: 12 | B23: December | C23: =INDEX('Budget Plan'!$B$24:$M$24,1,$A23) -> 10230 | D23: =SUMIFS(Expenses!$E$6:$E$405,Expenses!$A$6:$A$405,">="&DATE($C$4,$A23,1),Expenses!$A$6:$A$405,"<"&DATE($C$4,$A23+1,1)) -> 0 | E23: =C23-D23 -> 10230 | F23: =SUMIFS(Revenue!$C$6:$C$205,Revenue!$A$6:$A$205,">="&DATE($C$4,$A23,1),Revenue!$A$6:$A$205,"<"&DATE($C$4,$A23+1,1)) -> 0 | H23: =IF('Budget Plan'!A19="","",'Budget Plan'!A19) | I23: =IF($H23="","",'Budget Plan'!N19) | J23: =IF($H23="","",SUMIFS(Expenses!$E$6:$E$405,Expenses!$C$6:$C$405,$H23,Expenses!$A$6:$A$405,">="&DATE($C$4,1,1),Expenses!$A$6:$A$405,"<"&DATE($C$4+1,1,1))) | K23: =IF($H23="","",$I23-$J23) | L23: =IF(OR($H23="",$I23=0),"",$J23/$I23)
H24: =IF('Budget Plan'!A20="","",'Budget Plan'!A20) | I24: =IF($H24="","",'Budget Plan'!N20) | J24: =IF($H24="","",SUMIFS(Expenses!$E$6:$E$405,Expenses!$C$6:$C$405,$H24,Expenses!$A$6:$A$405,">="&DATE($C$4,1,1),Expenses!$A$6:$A$405,"<"&DATE($C$4+1,1,1))) | K24: =IF($H24="","",$I24-$J24) | L24: =IF(OR($H24="",$I24=0),"",$J24/$I24)
B25: Quarter by quarter | H25: =IF('Budget Plan'!A21="","",'Budget Plan'!A21) | I25: =IF($H25="","",'Budget Plan'!N21) | J25: =IF($H25="","",SUMIFS(Expenses!$E$6:$E$405,Expenses!$C$6:$C$405,$H25,Expenses!$A$6:$A$405,">="&DATE($C$4,1,1),Expenses!$A$6:$A$405,"<"&DATE($C$4+1,1,1))) | K25: =IF($H25="","",$I25-$J25) | L25: =IF(OR($H25="",$I25=0),"",$J25/$I25)
B26: Quarter | C26: Budget | D26: Spent | E26: Revenue | F26: Net | H26: =IF('Budget Plan'!A22="","",'Budget Plan'!A22) | I26: =IF($H26="","",'Budget Plan'!N22) | J26: =IF($H26="","",SUMIFS(Expenses!$E$6:$E$405,Expenses!$C$6:$C$405,$H26,Expenses!$A$6:$A$405,">="&DATE($C$4,1,1),Expenses!$A$6:$A$405,"<"&DATE($C$4+1,1,1))) | K26: =IF($H26="","",$I26-$J26) | L26: =IF(OR($H26="",$I26=0),"",$J26/$I26)
B27: Q1 | C27: =SUM(C12:C14) -> 30690 | D27: =SUM(D12:D14) -> 0 | E27: =SUM(F12:F14) -> 0 | F27: =E27-D27 -> 0 | H27: =IF('Budget Plan'!A23="","",'Budget Plan'!A23) | I27: =IF($H27="","",'Budget Plan'!N23) | J27: =IF($H27="","",SUMIFS(Expenses!$E$6:$E$405,Expenses!$C$6:$C$405,$H27,Expenses!$A$6:$A$405,">="&DATE($C$4,1,1),Expenses!$A$6:$A$405,"<"&DATE($C$4+1,1,1))) | K27: =IF($H27="","",$I27-$J27) | L27: =IF(OR($H27="",$I27=0),"",$J27/$I27)
B28: Q2 | C28: =SUM(C15:C17) -> 30690 | D28: =SUM(D15:D17) -> 0 | E28: =SUM(F15:F17) -> 0 | F28: =E28-D28 -> 0
B29: Q3 | C29: =SUM(C18:C20) -> 30690 | D29: =SUM(D18:D20) -> 17369 | E29: =SUM(F18:F20) -> 22550 | F29: =E29-D29 -> 5181 | H29: INSIGHTS — written automatically from your numbers
B30: Q4 | C30: =SUM(C21:C23) -> 30690 | D30: =SUM(D21:D23) -> 0 | E30: =SUM(F21:F23) -> 0 | F30: =E30-D30 -> 0 | H30: =IFERROR(IF($C$4=YEAR(TODAY()),TEXT((TODAY()-DATE($C$4,1,1)+1)/(DATE($C$4+1,1,1)-DATE($C$4,1,1)),"0%")&" of the year gone — "&TEXT($D$7/'Budget Plan'!$N$24,"0%")&" of the annual budget spent.","You spent "&TEXT($D$7/'Budget Plan'!$N$24,"0%")&" of the annual plan."),"") -> 61% of the year gone — 14% of the annual budget spent.
H31: =IFERROR(IF(OR($C$4<>YEAR(TODAY()),$D$7=0),"","On pace to spend "&TEXT($D$7/MONTH(TODAY())*12,"$#,##0")&" of the "&TEXT('Budget Plan'!$N$24,"$#,##0")&" plan."),"") -> On pace to spend $26,054 of the $122,760 plan.
H32: =IFERROR(IF(MAX($J$12:$J$27)=0,"","Largest cost: "&INDEX($H$12:$H$27,MATCH(MAX($J$12:$J$27),$J$12:$J$27,0))&" ("&TEXT(MAX($J$12:$J$27),"$#,##0")&" YTD)."),"") -> Largest cost: Payroll & contractors ($13,000 YTD).
H33: =IFERROR(IF($B$7=0,"","You keep "&TEXT($G$7/$B$7,"$0.00")&" of every revenue dollar."),"") -> You keep $0.23 of every revenue dollar.
