Workbook

Sheet Start Here
A1: Freelance Invoice + Income Tracker
A2: Send professional invoices and always know who owes you what.
B4: Welcome!
B5: This workbook gives you a fill-in invoice you can print or save as PDF, an income log, and a dashboard that tracks invoiced, collected, and outstanding money automatically.
B8: 1. Set up the Settings tab
C9: Add your business details, tax rate, payment terms, and your client list. The invoice and dropdowns pull from here.
B11: 2. Create an invoice
C12: On the Invoice tab, pick a client from the dropdown, add line items, then print or export to PDF (File > Save As > PDF).
B14: 3. Log it on the Income Log
C15: One row per invoice. Update the Status column when you get paid — the dashboard reads this table.
B17: 4. Watch the Dashboard
C18: Totals, monthly income chart, and per-client revenue update automatically. Set the year at the top.
B20: Color guide
C21: Light yellow cells = yours to fill in or change
C22: Grey / white cells = calculated automatically — no need to touch them
B24: Note: the file includes a few example rows so you can see how it works — just delete them and add your own.
B25: Works in Microsoft Excel (2016 or newer) and Google Sheets (upload to Drive, then Open with Google Sheets).
B26: Formulas are protected so you can't break anything by accident — every cell meant for typing is unlocked. To change anything else: Review → Unprotect Sheet (no password).

Sheet Settings
A1: Settings
A2: Your business info, invoice defaults, and client list. Yellow cells are yours to edit.
A4: YOUR BUSINESS
A5: Business / your name | B5: Alex Rivera Design
A6: Email | B6: alex@riveradesign.com
A7: Phone | B7: (555) 010-2266
A8: Address | B8: 410 Maple Ave, Portland, OR
A9: Payment instructions | B9: Pay by bank transfer to a/c 0000-1111 or PayPal alex@riveradesign.com
A11: INVOICE DEFAULTS
A12: Tax / VAT rate | B12: 0.085 | C12: Set to 0% if you don't charge tax.
A13: Invoice number prefix | B13: INV-
A14: Payment terms (days) | B14: 14 | C14: Due date = invoice date + this many days.
A16: CLIENT LIST | D16: Clients you add here appear in dropdowns on the Invoice and Income Log.
A17: Client | B17: Email | C17: Company / notes
A18: Acme Studios | B18: billing@acmestudios.com | C18: Acme Studios LLC
A19: Beacon Coffee Co. | B19: maya@beaconcoffee.com | C19: Ask for Maya

Sheet Invoice
A1: =IF(Settings!B5="","Your Business Name",Settings!B5) -> Alex Rivera Design
A2: =IF(Settings!B6="","",Settings!B6&" · "&Settings!B7) -> alex@riveradesign.com · (555) 010-2266
A3: =IF(Settings!B8="","",Settings!B8) -> 410 Maple Ave, Portland, OR
A5: INVOICE
A7: BILL TO | C7: Invoice # | D7: INV-003
A8: Acme Studios | C8: Invoice date | D8: 46083
A9: =IFERROR(INDEX(Settings!$B$18:$B$37,MATCH($A$8,Settings!$A$18:$A$37,0)),"") -> billing@acmestudios.com | C9: Due date | D9: =IF($D$8="","",$D$8+Settings!$B$14) -> 46097
A10: =IFERROR(INDEX(Settings!$C$18:$C$37,MATCH($A$8,Settings!$A$18:$A$37,0)),"") -> Acme Studios LLC
A12: Description | B12: Qty | C12: Rate | D12: Amount
A13: Monthly retainer — March | B13: 1 | C13: 600 | D13: =IF(OR($B13="",$C13=""),"",ROUND($B13*$C13,2)) -> 600
A14: Landing page copy revisions | B14: 2 | C14: 80 | D14: =IF(OR($B14="",$C14=""),"",ROUND($B14*$C14,2)) -> 160
D15: =IF(OR($B15="",$C15=""),"",ROUND($B15*$C15,2))
D16: =IF(OR($B16="",$C16=""),"",ROUND($B16*$C16,2))
D17: =IF(OR($B17="",$C17=""),"",ROUND($B17*$C17,2))
D18: =IF(OR($B18="",$C18=""),"",ROUND($B18*$C18,2))
D19: =IF(OR($B19="",$C19=""),"",ROUND($B19*$C19,2))
D20: =IF(OR($B20="",$C20=""),"",ROUND($B20*$C20,2))
D21: =IF(OR($B21="",$C21=""),"",ROUND($B21*$C21,2))
D22: =IF(OR($B22="",$C22=""),"",ROUND($B22*$C22,2))
D23: =IF(OR($B23="",$C23=""),"",ROUND($B23*$C23,2))
D24: =IF(OR($B24="",$C24=""),"",ROUND($B24*$C24,2))
C26: Subtotal | D26: =SUM(D13:D24) -> 760
C27: ="Tax ("&TEXT(Settings!$B$12,"0.0%")&")" -> Tax (8.5%) | D27: =ROUND(D26*Settings!$B$12,2) -> 64.6
C28: Total due | D28: =D26+D27 -> 824.6
A31: PAYMENT
A32: =IF(Settings!B9="","",Settings!B9) -> Pay by bank transfer to a/c 0000-1111 or PayPal alex@riveradesign.com
A34: Thank you for your business!

Sheet Income Log
A1: Income Log
A2: One row per invoice you send. The Dashboard reads this table automatically.
A4: Every cell in this table is yours to type in. Pick Client and Status from the dropdowns.
A5: Date | B5: Client | C5: Invoice # | D5: Description | E5: Amount | F5: Status | G5: Date paid
A6: 46034 | B6: Acme Studios | C6: INV-001 | D6: Website design project | E6: 1520 | F6: Paid | G6: 46042
A7: 46056 | B7: Beacon Coffee Co. | C7: INV-002 | D7: Brand refresh | E7: 850 | F7: Paid | G7: 46068
A8: 46083 | B8: Acme Studios | C8: INV-003 | D8: Monthly retainer — March | E8: 600 | F8: Sent

Sheet Dashboard
A1: Dashboard
A2: Your money at a glance. Everything here updates automatically from the Income Log.
B4: Year | C4: 2026
B6: TOTAL INVOICED | E6: COLLECTED | H6: OUTSTANDING | K6: INVOICES SENT
B7: =SUMIFS('Income Log'!$E$6:$E$105,'Income Log'!$A$6:$A$105,">="&DATE($C$4,1,1),'Income Log'!$A$6:$A$105,"<"&DATE($C$4+1,1,1)) -> 2970 | E7: =SUMIFS('Income Log'!$E$6:$E$105,'Income Log'!$F$6:$F$105,"Paid",'Income Log'!$A$6:$A$105,">="&DATE($C$4,1,1),'Income Log'!$A$6:$A$105,"<"&DATE($C$4+1,1,1)) -> 2370 | H7: =B7-E7 -> 600 | K7: =COUNTIFS('Income Log'!$A$6:$A$105,">="&DATE($C$4,1,1),'Income Log'!$A$6:$A$105,"<"&DATE($C$4+1,1,1)) -> 3
B9: AVG DAYS TO PAY | E9: COLLECTION RATE | H9: AVG INVOICE | K9: OVERDUE AMOUNT
B10: =IFERROR(ROUND(SUMPRODUCT(('Income Log'!$G$6:$G$105-'Income Log'!$A$6:$A$105)*('Income Log'!$G$6:$G$105<>"")*(YEAR('Income Log'!$A$6:$A$105)=$C$4))/SUMPRODUCT(('Income Log'!$G$6:$G$105<>"")*(YEAR('Income Log'!$A$6:$A$105)=$C$4)*1),1),"—") -> 10 | E10: =IF(B7=0,"",E7/B7) -> 0.7979798 | H10: =IF(K7=0,"",B7/K7) -> 990 | K10: =SUMIFS('Income Log'!$E$6:$E$105,'Income Log'!$F$6:$F$105,"Overdue",'Income Log'!$A$6:$A$105,">="&DATE($C$4,1,1),'Income Log'!$A$6:$A$105,"<"&DATE($C$4+1,1,1)) -> 0
B13: Invoiced by month | H13: Revenue by client
A14: # | B14: Month | C14: Invoiced | H14: Client | I14: Invoiced
A15: 1 | B15: January | C15: =SUMIFS('Income Log'!$E$6:$E$105,'Income Log'!$A$6:$A$105,">="&DATE($C$4,$A15,1),'Income Log'!$A$6:$A$105,"<"&DATE($C$4,$A15+1,1)) -> 1520 | H15: =IF(Settings!A18="","",Settings!A18) -> Acme Studios | I15: =IF($H15="","",SUMIFS('Income Log'!$E$6:$E$105,'Income Log'!$B$6:$B$105,$H15,'Income Log'!$A$6:$A$105,">="&DATE($C$4,1,1),'Income Log'!$A$6:$A$105,"<"&DATE($C$4+1,1,1))) -> 2120
A16: 2 | B16: February | C16: =SUMIFS('Income Log'!$E$6:$E$105,'Income Log'!$A$6:$A$105,">="&DATE($C$4,$A16,1),'Income Log'!$A$6:$A$105,"<"&DATE($C$4,$A16+1,1)) -> 850 | H16: =IF(Settings!A19="","",Settings!A19) -> Beacon Coffee Co. | I16: =IF($H16="","",SUMIFS('Income Log'!$E$6:$E$105,'Income Log'!$B$6:$B$105,$H16,'Income Log'!$A$6:$A$105,">="&DATE($C$4,1,1),'Income Log'!$A$6:$A$105,"<"&DATE($C$4+1,1,1))) -> 850
A17: 3 | B17: March | C17: =SUMIFS('Income Log'!$E$6:$E$105,'Income Log'!$A$6:$A$105,">="&DATE($C$4,$A17,1),'Income Log'!$A$6:$A$105,"<"&DATE($C$4,$A17+1,1)) -> 600 | H17: =IF(Settings!A20="","",Settings!A20) | I17: =IF($H17="","",SUMIFS('Income Log'!$E$6:$E$105,'Income Log'!$B$6:$B$105,$H17,'Income Log'!$A$6:$A$105,">="&DATE($C$4,1,1),'Income Log'!$A$6:$A$105,"<"&DATE($C$4+1,1,1)))
A18: 4 | B18: April | C18: =SUMIFS('Income Log'!$E$6:$E$105,'Income Log'!$A$6:$A$105,">="&DATE($C$4,$A18,1),'Income Log'!$A$6:$A$105,"<"&DATE($C$4,$A18+1,1)) -> 0 | H18: =IF(Settings!A21="","",Settings!A21) | I18: =IF($H18="","",SUMIFS('Income Log'!$E$6:$E$105,'Income Log'!$B$6:$B$105,$H18,'Income Log'!$A$6:$A$105,">="&DATE($C$4,1,1),'Income Log'!$A$6:$A$105,"<"&DATE($C$4+1,1,1)))
A19: 5 | B19: May | C19: =SUMIFS('Income Log'!$E$6:$E$105,'Income Log'!$A$6:$A$105,">="&DATE($C$4,$A19,1),'Income Log'!$A$6:$A$105,"<"&DATE($C$4,$A19+1,1)) -> 0 | H19: =IF(Settings!A22="","",Settings!A22) | I19: =IF($H19="","",SUMIFS('Income Log'!$E$6:$E$105,'Income Log'!$B$6:$B$105,$H19,'Income Log'!$A$6:$A$105,">="&DATE($C$4,1,1),'Income Log'!$A$6:$A$105,"<"&DATE($C$4+1,1,1)))
A20: 6 | B20: June | C20: =SUMIFS('Income Log'!$E$6:$E$105,'Income Log'!$A$6:$A$105,">="&DATE($C$4,$A20,1),'Income Log'!$A$6:$A$105,"<"&DATE($C$4,$A20+1,1)) -> 0 | H20: =IF(Settings!A23="","",Settings!A23) | I20: =IF($H20="","",SUMIFS('Income Log'!$E$6:$E$105,'Income Log'!$B$6:$B$105,$H20,'Income Log'!$A$6:$A$105,">="&DATE($C$4,1,1),'Income Log'!$A$6:$A$105,"<"&DATE($C$4+1,1,1)))
A21: 7 | B21: July | C21: =SUMIFS('Income Log'!$E$6:$E$105,'Income Log'!$A$6:$A$105,">="&DATE($C$4,$A21,1),'Income Log'!$A$6:$A$105,"<"&DATE($C$4,$A21+1,1)) -> 0 | H21: =IF(Settings!A24="","",Settings!A24) | I21: =IF($H21="","",SUMIFS('Income Log'!$E$6:$E$105,'Income Log'!$B$6:$B$105,$H21,'Income Log'!$A$6:$A$105,">="&DATE($C$4,1,1),'Income Log'!$A$6:$A$105,"<"&DATE($C$4+1,1,1)))
A22: 8 | B22: August | C22: =SUMIFS('Income Log'!$E$6:$E$105,'Income Log'!$A$6:$A$105,">="&DATE($C$4,$A22,1),'Income Log'!$A$6:$A$105,"<"&DATE($C$4,$A22+1,1)) -> 0 | H22: =IF(Settings!A25="","",Settings!A25) | I22: =IF($H22="","",SUMIFS('Income Log'!$E$6:$E$105,'Income Log'!$B$6:$B$105,$H22,'Income Log'!$A$6:$A$105,">="&DATE($C$4,1,1),'Income Log'!$A$6:$A$105,"<"&DATE($C$4+1,1,1)))
A23: 9 | B23: September | C23: =SUMIFS('Income Log'!$E$6:$E$105,'Income Log'!$A$6:$A$105,">="&DATE($C$4,$A23,1),'Income Log'!$A$6:$A$105,"<"&DATE($C$4,$A23+1,1)) -> 0 | H23: =IF(Settings!A26="","",Settings!A26) | I23: =IF($H23="","",SUMIFS('Income Log'!$E$6:$E$105,'Income Log'!$B$6:$B$105,$H23,'Income Log'!$A$6:$A$105,">="&DATE($C$4,1,1),'Income Log'!$A$6:$A$105,"<"&DATE($C$4+1,1,1)))
A24: 10 | B24: October | C24: =SUMIFS('Income Log'!$E$6:$E$105,'Income Log'!$A$6:$A$105,">="&DATE($C$4,$A24,1),'Income Log'!$A$6:$A$105,"<"&DATE($C$4,$A24+1,1)) -> 0 | H24: =IF(Settings!A27="","",Settings!A27) | I24: =IF($H24="","",SUMIFS('Income Log'!$E$6:$E$105,'Income Log'!$B$6:$B$105,$H24,'Income Log'!$A$6:$A$105,">="&DATE($C$4,1,1),'Income Log'!$A$6:$A$105,"<"&DATE($C$4+1,1,1)))
A25: 11 | B25: November | C25: =SUMIFS('Income Log'!$E$6:$E$105,'Income Log'!$A$6:$A$105,">="&DATE($C$4,$A25,1),'Income Log'!$A$6:$A$105,"<"&DATE($C$4,$A25+1,1)) -> 0 | H25: =IF(Settings!A28="","",Settings!A28) | I25: =IF($H25="","",SUMIFS('Income Log'!$E$6:$E$105,'Income Log'!$B$6:$B$105,$H25,'Income Log'!$A$6:$A$105,">="&DATE($C$4,1,1),'Income Log'!$A$6:$A$105,"<"&DATE($C$4+1,1,1)))
A26: 12 | B26: December | C26: =SUMIFS('Income Log'!$E$6:$E$105,'Income Log'!$A$6:$A$105,">="&DATE($C$4,$A26,1),'Income Log'!$A$6:$A$105,"<"&DATE($C$4,$A26+1,1)) -> 0 | H26: =IF(Settings!A29="","",Settings!A29) | I26: =IF($H26="","",SUMIFS('Income Log'!$E$6:$E$105,'Income Log'!$B$6:$B$105,$H26,'Income Log'!$A$6:$A$105,">="&DATE($C$4,1,1),'Income Log'!$A$6:$A$105,"<"&DATE($C$4+1,1,1)))
H27: =IF(Settings!A30="","",Settings!A30) | I27: =IF($H27="","",SUMIFS('Income Log'!$E$6:$E$105,'Income Log'!$B$6:$B$105,$H27,'Income Log'!$A$6:$A$105,">="&DATE($C$4,1,1),'Income Log'!$A$6:$A$105,"<"&DATE($C$4+1,1,1)))
B28: Quarter by quarter | H28: =IF(Settings!A31="","",Settings!A31) | I28: =IF($H28="","",SUMIFS('Income Log'!$E$6:$E$105,'Income Log'!$B$6:$B$105,$H28,'Income Log'!$A$6:$A$105,">="&DATE($C$4,1,1),'Income Log'!$A$6:$A$105,"<"&DATE($C$4+1,1,1)))
A29: # | B29: Quarter | C29: Invoiced | D29: Collected | H29: =IF(Settings!A32="","",Settings!A32) | I29: =IF($H29="","",SUMIFS('Income Log'!$E$6:$E$105,'Income Log'!$B$6:$B$105,$H29,'Income Log'!$A$6:$A$105,">="&DATE($C$4,1,1),'Income Log'!$A$6:$A$105,"<"&DATE($C$4+1,1,1)))
A30: 1 | B30: Q1 | C30: =SUMIFS('Income Log'!$E$6:$E$105,'Income Log'!$A$6:$A$105,">="&DATE($C$4,3*$A30-2,1),'Income Log'!$A$6:$A$105,"<"&DATE($C$4,3*$A30+1,1)) -> 2970 | D30: =SUMIFS('Income Log'!$E$6:$E$105,'Income Log'!$F$6:$F$105,"Paid",'Income Log'!$A$6:$A$105,">="&DATE($C$4,3*$A30-2,1),'Income Log'!$A$6:$A$105,"<"&DATE($C$4,3*$A30+1,1)) -> 2370 | H30: =IF(Settings!A33="","",Settings!A33) | I30: =IF($H30="","",SUMIFS('Income Log'!$E$6:$E$105,'Income Log'!$B$6:$B$105,$H30,'Income Log'!$A$6:$A$105,">="&DATE($C$4,1,1),'Income Log'!$A$6:$A$105,"<"&DATE($C$4+1,1,1)))
A31: 2 | B31: Q2 | C31: =SUMIFS('Income Log'!$E$6:$E$105,'Income Log'!$A$6:$A$105,">="&DATE($C$4,3*$A31-2,1),'Income Log'!$A$6:$A$105,"<"&DATE($C$4,3*$A31+1,1)) -> 0 | D31: =SUMIFS('Income Log'!$E$6:$E$105,'Income Log'!$F$6:$F$105,"Paid",'Income Log'!$A$6:$A$105,">="&DATE($C$4,3*$A31-2,1),'Income Log'!$A$6:$A$105,"<"&DATE($C$4,3*$A31+1,1)) -> 0 | H31: =IF(Settings!A34="","",Settings!A34) | I31: =IF($H31="","",SUMIFS('Income Log'!$E$6:$E$105,'Income Log'!$B$6:$B$105,$H31,'Income Log'!$A$6:$A$105,">="&DATE($C$4,1,1),'Income Log'!$A$6:$A$105,"<"&DATE($C$4+1,1,1)))
A32: 3 | B32: Q3 | C32: =SUMIFS('Income Log'!$E$6:$E$105,'Income Log'!$A$6:$A$105,">="&DATE($C$4,3*$A32-2,1),'Income Log'!$A$6:$A$105,"<"&DATE($C$4,3*$A32+1,1)) -> 0 | D32: =SUMIFS('Income Log'!$E$6:$E$105,'Income Log'!$F$6:$F$105,"Paid",'Income Log'!$A$6:$A$105,">="&DATE($C$4,3*$A32-2,1),'Income Log'!$A$6:$A$105,"<"&DATE($C$4,3*$A32+1,1)) -> 0 | H32: =IF(Settings!A35="","",Settings!A35) | I32: =IF($H32="","",SUMIFS('Income Log'!$E$6:$E$105,'Income Log'!$B$6:$B$105,$H32,'Income Log'!$A$6:$A$105,">="&DATE($C$4,1,1),'Income Log'!$A$6:$A$105,"<"&DATE($C$4+1,1,1)))
A33: 4 | B33: Q4 | C33: =SUMIFS('Income Log'!$E$6:$E$105,'Income Log'!$A$6:$A$105,">="&DATE($C$4,3*$A33-2,1),'Income Log'!$A$6:$A$105,"<"&DATE($C$4,3*$A33+1,1)) -> 0 | D33: =SUMIFS('Income Log'!$E$6:$E$105,'Income Log'!$F$6:$F$105,"Paid",'Income Log'!$A$6:$A$105,">="&DATE($C$4,3*$A33-2,1),'Income Log'!$A$6:$A$105,"<"&DATE($C$4,3*$A33+1,1)) -> 0 | H33: =IF(Settings!A36="","",Settings!A36) | I33: =IF($H33="","",SUMIFS('Income Log'!$E$6:$E$105,'Income Log'!$B$6:$B$105,$H33,'Income Log'!$A$6:$A$105,">="&DATE($C$4,1,1),'Income Log'!$A$6:$A$105,"<"&DATE($C$4+1,1,1)))
H34: =IF(Settings!A37="","",Settings!A37) | I34: =IF($H34="","",SUMIFS('Income Log'!$E$6:$E$105,'Income Log'!$B$6:$B$105,$H34,'Income Log'!$A$6:$A$105,">="&DATE($C$4,1,1),'Income Log'!$A$6:$A$105,"<"&DATE($C$4+1,1,1)))
B35: INSIGHTS — written automatically from your numbers
B36: =IFERROR(IF($H$7=0,"Everything invoiced this year has been collected.",TEXT(COUNTIFS('Income Log'!$F$6:$F$105,"<>Paid",'Income Log'!$E$6:$E$105,">0",'Income Log'!$A$6:$A$105,">="&DATE($C$4,1,1),'Income Log'!$A$6:$A$105,"<"&DATE($C$4+1,1,1)),"0")&" invoice(s) worth "&TEXT($H$7,"$#,##0")&" are still unpaid."),"") -> 1 invoice(s) worth $600 are still unpaid.
B37: =IFERROR(IF(MAX($C$15:$C$26)=0,"","Busiest month: "&INDEX($B$15:$B$26,MATCH(MAX($C$15:$C$26),$C$15:$C$26,0))&" ("&TEXT(MAX($C$15:$C$26),"$#,##0")&" invoiced)."),"") -> Busiest month: January ($1,520 invoiced).
B38: =IFERROR(IF($H$7=0,"","Oldest unpaid invoice is "&TEXT(TODAY()-_xlfn.MINIFS('Income Log'!$A$6:$A$105,'Income Log'!$F$6:$F$105,"<>Paid",'Income Log'!$E$6:$E$105,">0"),"0")&" days old — worth a nudge."),"") -> Oldest unpaid invoice is 163 days old — worth a nudge.
B39: =IFERROR(IF($B$7=0,"","Top client: "&INDEX($H$15:$H$34,MATCH(MAX($I$15:$I$34),$I$15:$I$34,0))&" — "&TEXT(MAX($I$15:$I$34)/$B$7,"0%")&" of the year."),"") -> Top client: Acme Studios — 71% of the year.
