Workbook

Sheet Start Here
A1: Paycheck Budget Planner
A2: Budget per paycheck, not per month — give every dollar a job before payday.
B4: Welcome!
B5: If your money runs on paydays instead of calendar months, monthly budgets never quite fit. This planner works the way you're paid: one column per check — assign it to bills, spending, and savings until Left to Assign hits zero.
B8: 1. Set up your basics
C9: On Setup: how often you're paid, your typical check, and your bills with amounts and due days.
B11: 2. Plan each paycheck
C12: On the Planner, enter the check date and amount, then fill in what this check covers — bills first, then spending, then savings.
B14: 3. Drive Left to Assign to zero
C15: Green zero = every dollar has a job. Amber = money still unassigned. Red = you've planned more than the check.
B17: 4. Repeat each payday
C18: Twelve check columns ≈ six months biweekly. Right-click the tab to duplicate it for the next stretch.
B20: Color guide
C21: Light yellow cells = yours to fill in or change
C22: Grey / white cells = calculated automatically — no need to touch them
B24: Note: the first two checks are filled in as examples — clear them and plan your own.
B25: Works in Microsoft Excel (2016 or newer) and Google Sheets (upload to Drive, then Open with Google Sheets).
B26: Formulas are protected so you can't break anything by accident — every cell meant for typing is unlocked. To change anything else: Review → Unprotect Sheet (no password).

Sheet Setup
A1: Setup
A2: Your pay rhythm and your bills. Yellow cells are yours to edit.
A5: PAYCHECK BASICS
A6: Pay frequency | B6: Every 2 weeks
A7: Typical check (after tax) | B7: 1650
A9: BILLS | C9: Bill names appear on the Planner automatically.
A10: Bill | B10: Amount | C10: Due day
A11: Rent | B11: 1600 | C11: 1
A12: Internet | B12: 60 | C12: 12
A13: Phone | B13: 35 | C13: 15
A14: Car insurance | B14: 140 | C14: 20
A24: Total monthly bills | B24: =SUM(B11:B22) -> 1835

Sheet Paycheck Planner
A1: Paycheck Planner
A2: One column per check. Assign every dollar until Left to Assign reads zero.
A4: Yellow cells are yours. Start with the check date and income, then work down.
A6: Check date | B6: 46241 | C6: 46255
A7: Income | B7: 1650 | C7: 1650
A9: BILLS (names come from Setup)
A10: =IF(Setup!A11="","",Setup!A11) -> Rent | B10: 1600
A11: =IF(Setup!A12="","",Setup!A12) -> Internet | C11: 60
A12: =IF(Setup!A13="","",Setup!A13) -> Phone | C12: 35
A13: =IF(Setup!A14="","",Setup!A14) -> Car insurance | C13: 140
A14: =IF(Setup!A15="","",Setup!A15)
A15: =IF(Setup!A16="","",Setup!A16)
A16: =IF(Setup!A17="","",Setup!A17)
A17: =IF(Setup!A18="","",Setup!A18)
A18: =IF(Setup!A19="","",Setup!A19)
A19: =IF(Setup!A20="","",Setup!A20)
A20: =IF(Setup!A21="","",Setup!A21)
A21: =IF(Setup!A22="","",Setup!A22)
A22: SPENDING
A23: Groceries | B23: 40 | C23: 300
A24: Dining out | C24: 80
A25: Gas & transport | C25: 60
A26: Fun money | C26: 75
A27: Household | C27: 40
A28: Personal care
A31: SAVINGS & DEBT
A32: Savings | B32: 10 | C32: 800
A33: Extra debt payment | C33: 60
A37: Assigned | B37: =SUM(B10:B21)+SUM(B23:B30)+SUM(B32:B35) -> 1650 | C37: =SUM(C10:C21)+SUM(C23:C30)+SUM(C32:C35) -> 1650 | D37: =SUM(D10:D21)+SUM(D23:D30)+SUM(D32:D35) -> 0 | E37: =SUM(E10:E21)+SUM(E23:E30)+SUM(E32:E35) -> 0 | F37: =SUM(F10:F21)+SUM(F23:F30)+SUM(F32:F35) -> 0 | G37: =SUM(G10:G21)+SUM(G23:G30)+SUM(G32:G35) -> 0 | H37: =SUM(H10:H21)+SUM(H23:H30)+SUM(H32:H35) -> 0 | I37: =SUM(I10:I21)+SUM(I23:I30)+SUM(I32:I35) -> 0 | ... M37: =SUM(M10:M21)+SUM(M23:M30)+SUM(M32:M35) -> 0
A38: Left to assign | B38: =IF(B$7="","",B$7-B37) -> 0 | C38: =IF(C$7="","",C$7-C37) -> 0 | D38: =IF(D$7="","",D$7-D37) | E38: =IF(E$7="","",E$7-E37) | F38: =IF(F$7="","",F$7-F37) | G38: =IF(G$7="","",G$7-G37) | H38: =IF(H$7="","",H$7-H37) | I38: =IF(I$7="","",I$7-I37) | ... M38: =IF(M$7="","",M$7-M37)
