Workbook

Sheet Start Here
A1: Personal Budget Dashboard
A2: Monthly budget, annual overview, savings goals, and bills — one file.
B4: Welcome!
B5: Set your budgets once, log your spending as you go, and this file does the rest: budget vs. actual for any month, a year-at-a-glance heatmap, savings goal math, and a bill list so nothing sneaks up on you.
B8: 1. Set up your budget
C9: On Budget Setup, enter monthly income and a budget per category. Rename categories to fit your life.
B11: 2. List your bills
C12: On Bills: what, how much, which day it's due, autopay or not. Know your fixed costs at a glance.
B14: 3. Face your debts
C15: On Debt Payoff: balance, APR, payment — see when each debt is gone, and what an extra payment changes.
B17: 4. Log your spending
C18: On Transactions, one row per purchase: date, what it was, category (dropdown), amount. Ten seconds.
B20: 5. Check the Dashboard
C21: Pick a month — budget vs. actual per category with progress bars, orange at 80%, red when over.
B23: 6. Zoom out on Year Overview
C24: Twelve months of spending, a trend chart, and a category-by-month heatmap that shows patterns.
B26: 7. Fund your Savings Goals
C27: Set a target and a date; the sheet tells you how much per month gets you there.
B29: Color guide
C30: Light yellow cells = yours to fill in or change
C31: Grey / white cells = calculated automatically — no need to touch them
B33: Note: the file includes example data so you can see how everything works — delete it and add your own.
B34: Works in Microsoft Excel (2016 or newer) and Google Sheets (upload to Drive, then Open with Google Sheets).
B35: Formulas are protected so you can't break anything by accident — every cell meant for typing is unlocked. To change anything else: Review → Unprotect Sheet (no password).

Sheet Budget Setup
A1: Budget Setup
A2: Your income and monthly budgets. Yellow cells are yours to edit.
A5: MONTHLY INCOME
A6: Source | B6: Monthly amount
A7: Paycheck (after tax) | B7: 4200
A8: Side hustle | B8: 350
A13: MONTHLY BUDGETS | D13: Rename, add, or remove categories — dropdowns and every view follow this list.
A14: Category | B14: Monthly budget
A15: Housing | B15: 1600
A16: Groceries | B16: 550
A17: Dining out | B17: 250
A18: Transport | B18: 200
A19: Utilities | B19: 180
A20: Phone & internet | B20: 95
A21: Insurance | B21: 140
A22: Health & fitness | B22: 90
A23: Entertainment | B23: 120
A24: Subscriptions | B24: 60
A25: Shopping | B25: 150
A26: Personal care | B26: 70
... A29: Everything else | B29: 150
A36: Total budgeted | B36: =SUM(B15:B34) -> 4455

Sheet Bills
A1: Bills
A2: Your recurring bills, sorted by due day — so nothing sneaks up on you.
A4: Every cell in this table is yours to type in. Tip: enter bills in due-day order.
A5: Bill | B5: Amount | C5: Due day | D5: Autopay? | E5: Notes
A6: Rent | B6: 1600 | C6: 1 | D6: No | E6: Counts toward the Housing budget
A7: Internet | B7: 60 | C7: 12 | D7: Yes
A8: Phone | B8: 35 | C8: 15 | D8: Yes
A9: Car insurance | B9: 140 | C9: 20 | D9: Yes
A27: Total monthly bills | B27: =SUM(B6:B25) -> 1835 | C27: Make sure each bill is inside one of your category budgets.

Sheet Debt Payoff
A1: Debt Payoff
A2: See when each debt is gone — and what one extra payment per month changes.
A4: Fill in the yellow columns. Months, payoff date, and interest calculate themselves.
A5: Debt | B5: Balance | C5: APR | D5: Monthly payment | E5: Months to payoff | F5: Debt-free by | G5: Interest you'll pay
A6: Credit card | B6: 2400 | C6: 0.229 | D6: 120 | E6: =IF(OR($A6="",$B6="",$D6=""),"",IFERROR(ROUNDUP(NPER($C6/12,-$D6,$B6),0),"Payment too small")) -> 26 | F6: =IF(ISNUMBER($E6),EDATE(TODAY(),$E6),"") -> 47037 | G6: =IF(ISNUMBER($E6),ROUND($D6*NPER($C6/12,-$D6,$B6)-$B6,2),"") -> 651.67
A7: Interest-free financing | B7: 850 | C7: 0 | D7: 50 | E7: =IF(OR($A7="",$B7="",$D7=""),"",IFERROR(ROUNDUP(NPER($C7/12,-$D7,$B7),0),"Payment too small")) -> 17 | F7: =IF(ISNUMBER($E7),EDATE(TODAY(),$E7),"") -> 46763 | G7: =IF(ISNUMBER($E7),ROUND($D7*NPER($C7/12,-$D7,$B7)-$B7,2),"") -> 0
E8: =IF(OR($A8="",$B8="",$D8=""),"",IFERROR(ROUNDUP(NPER($C8/12,-$D8,$B8),0),"Payment too small")) | F8: =IF(ISNUMBER($E8),EDATE(TODAY(),$E8),"") | G8: =IF(ISNUMBER($E8),ROUND($D8*NPER($C8/12,-$D8,$B8)-$B8,2),"")
E9: =IF(OR($A9="",$B9="",$D9=""),"",IFERROR(ROUNDUP(NPER($C9/12,-$D9,$B9),0),"Payment too small")) | F9: =IF(ISNUMBER($E9),EDATE(TODAY(),$E9),"") | G9: =IF(ISNUMBER($E9),ROUND($D9*NPER($C9/12,-$D9,$B9)-$B9,2),"")
E10: =IF(OR($A10="",$B10="",$D10=""),"",IFERROR(ROUNDUP(NPER($C10/12,-$D10,$B10),0),"Payment too small")) | F10: =IF(ISNUMBER($E10),EDATE(TODAY(),$E10),"") | G10: =IF(ISNUMBER($E10),ROUND($D10*NPER($C10/12,-$D10,$B10)-$B10,2),"")
E11: =IF(OR($A11="",$B11="",$D11=""),"",IFERROR(ROUNDUP(NPER($C11/12,-$D11,$B11),0),"Payment too small")) | F11: =IF(ISNUMBER($E11),EDATE(TODAY(),$E11),"") | G11: =IF(ISNUMBER($E11),ROUND($D11*NPER($C11/12,-$D11,$B11)-$B11,2),"")
E12: =IF(OR($A12="",$B12="",$D12=""),"",IFERROR(ROUNDUP(NPER($C12/12,-$D12,$B12),0),"Payment too small")) | F12: =IF(ISNUMBER($E12),EDATE(TODAY(),$E12),"") | G12: =IF(ISNUMBER($E12),ROUND($D12*NPER($C12/12,-$D12,$B12)-$B12,2),"")
E13: =IF(OR($A13="",$B13="",$D13=""),"",IFERROR(ROUNDUP(NPER($C13/12,-$D13,$B13),0),"Payment too small")) | F13: =IF(ISNUMBER($E13),EDATE(TODAY(),$E13),"") | G13: =IF(ISNUMBER($E13),ROUND($D13*NPER($C13/12,-$D13,$B13)-$B13,2),"")
E14: =IF(OR($A14="",$B14="",$D14=""),"",IFERROR(ROUNDUP(NPER($C14/12,-$D14,$B14),0),"Payment too small")) | F14: =IF(ISNUMBER($E14),EDATE(TODAY(),$E14),"") | G14: =IF(ISNUMBER($E14),ROUND($D14*NPER($C14/12,-$D14,$B14)-$B14,2),"")
E15: =IF(OR($A15="",$B15="",$D15=""),"",IFERROR(ROUNDUP(NPER($C15/12,-$D15,$B15),0),"Payment too small")) | F15: =IF(ISNUMBER($E15),EDATE(TODAY(),$E15),"") | G15: =IF(ISNUMBER($E15),ROUND($D15*NPER($C15/12,-$D15,$B15)-$B15,2),"")
A17: Total | B17: =SUM(B6:B15) -> 3250 | D17: =SUM(D6:D15) -> 170
A19: The extra-payment effect
A20: Extra per month | B20: 50
A21: Applied to (highest APR) | B21: =IFERROR(INDEX($A$6:$A$15,MATCH(MAX($C$6:$C$15),$C$6:$C$15,0)),"") -> Credit card
A22: Paid off in | B22: =IF(OR($B$21="",$B$25=""),"",IFERROR(ROUNDUP(NPER($C$25,-($D$25+$B$20),$B$25),0),"—")) -> 17 | C22: =IF($B$22="","","months — instead of "&IFERROR(ROUNDUP(NPER($C$25,-$D$25,$B$25),0),"—")) -> months — instead of 26
A23: Interest saved ≈ | B23: =IF(OR($B$21="",$B$25=""),"",IFERROR(ROUND($D$25*NPER($C$25,-$D$25,$B$25)-($D$25+$B$20)*NPER($C$25,-($D$25+$B$20),$B$25),2),"")) -> 228.71
A25: internals → | B25: =IFERROR(INDEX($B$6:$B$15,MATCH(MAX($C$6:$C$15),$C$6:$C$15,0)),"") -> 2400 | C25: =IFERROR(MAX($C$6:$C$15)/12,"") -> 0.019083333 | D25: =IFERROR(INDEX($D$6:$D$15,MATCH(MAX($C$6:$C$15),$C$6:$C$15,0)),"") -> 120
A27: Avalanche method: extra money goes to the highest-APR debt first — it saves the most interest.
A28: Estimates assume monthly compounding at a fixed APR; card interest actually compounds daily, so treat dates as close, not exact.

Sheet Transactions
A1: Transactions
A2: One row per purchase. Every view in this file reads this table.
A4: Every cell in this table is yours to type in. Pick the Category from the dropdown.
A5: Date | B5: Description | C5: Category | D5: Amount
A6: 46204 | B6: Rent | C6: Housing | D6: 1600
A7: 46209 | B7: Groceries week 1 | C7: Groceries | D7: 96.4
A8: 46221 | B8: Concert tickets | C8: Entertainment | D8: 89
A9: 46227 | B9: Groceries week 3 | C9: Groceries | D9: 88.1
A10: 46235 | B10: Rent | C10: Housing | D10: 1600
A11: 46237 | B11: Trader Joe's run | C11: Groceries | D11: 84.2
A12: 46239 | B12: Gas fill-up | C12: Transport | D12: 42.5
A13: 46242 | B13: Dinner with friends | C13: Dining out | D13: 56.8

Sheet Dashboard
A1: Dashboard
A2: Pick a month — everything below updates automatically.
A4: Month (1–12) | B4: 8 | C4: Year | D4: 2026 | E4: =CHOOSE($B$4,"January","February","March","April","May","June","July","August","September","October","November","December")&" "&$D$4 -> August 2026
A6: MONTHLY INCOME | C6: BUDGETED | E6: SPENT THIS MONTH | H6: LEFT TO SPEND
A7: =SUM('Budget Setup'!$B$7:$B$10) -> 4550 | C7: =SUM('Budget Setup'!$B$15:$B$34) -> 4455 | E7: =SUMIFS(Transactions!$D$6:$D$305,Transactions!$A$6:$A$305,">="&DATE($D$4,$B$4,1),Transactions!$A$6:$A$305,"<"&DATE($D$4,$B$4+1,1)) -> 1783.5 | H7: =C7-E7 -> 2671.5
A10: Budget vs. actual
A11: Category | B11: Budget | C11: Spent | D11: Left | E11: % used
A12: =IF('Budget Setup'!A15="","",'Budget Setup'!A15) -> Housing | B12: =IF($A12="","",'Budget Setup'!B15) -> 1600 | C12: =IF($A12="","",SUMIFS(Transactions!$D$6:$D$305,Transactions!$C$6:$C$305,$A12,Transactions!$A$6:$A$305,">="&DATE($D$4,$B$4,1),Transactions!$A$6:$A$305,"<"&DATE($D$4,$B$4+1,1))) -> 1600 | D12: =IF($A12="","",$B12-$C12) -> 0 | E12: =IF(OR($A12="",$B12=0),"",$C12/$B12) -> 1
A13: =IF('Budget Setup'!A16="","",'Budget Setup'!A16) -> Groceries | B13: =IF($A13="","",'Budget Setup'!B16) -> 550 | C13: =IF($A13="","",SUMIFS(Transactions!$D$6:$D$305,Transactions!$C$6:$C$305,$A13,Transactions!$A$6:$A$305,">="&DATE($D$4,$B$4,1),Transactions!$A$6:$A$305,"<"&DATE($D$4,$B$4+1,1))) -> 84.2 | D13: =IF($A13="","",$B13-$C13) -> 465.8 | E13: =IF(OR($A13="",$B13=0),"",$C13/$B13) -> 0.15309091
A14: =IF('Budget Setup'!A17="","",'Budget Setup'!A17) -> Dining out | B14: =IF($A14="","",'Budget Setup'!B17) -> 250 | C14: =IF($A14="","",SUMIFS(Transactions!$D$6:$D$305,Transactions!$C$6:$C$305,$A14,Transactions!$A$6:$A$305,">="&DATE($D$4,$B$4,1),Transactions!$A$6:$A$305,"<"&DATE($D$4,$B$4+1,1))) -> 56.8 | D14: =IF($A14="","",$B14-$C14) -> 193.2 | E14: =IF(OR($A14="",$B14=0),"",$C14/$B14) -> 0.2272
A15: =IF('Budget Setup'!A18="","",'Budget Setup'!A18) -> Transport | B15: =IF($A15="","",'Budget Setup'!B18) -> 200 | C15: =IF($A15="","",SUMIFS(Transactions!$D$6:$D$305,Transactions!$C$6:$C$305,$A15,Transactions!$A$6:$A$305,">="&DATE($D$4,$B$4,1),Transactions!$A$6:$A$305,"<"&DATE($D$4,$B$4+1,1))) -> 42.5 | D15: =IF($A15="","",$B15-$C15) -> 157.5 | E15: =IF(OR($A15="",$B15=0),"",$C15/$B15) -> 0.2125
A16: =IF('Budget Setup'!A19="","",'Budget Setup'!A19) -> Utilities | B16: =IF($A16="","",'Budget Setup'!B19) -> 180 | C16: =IF($A16="","",SUMIFS(Transactions!$D$6:$D$305,Transactions!$C$6:$C$305,$A16,Transactions!$A$6:$A$305,">="&DATE($D$4,$B$4,1),Transactions!$A$6:$A$305,"<"&DATE($D$4,$B$4+1,1))) -> 0 | D16: =IF($A16="","",$B16-$C16) -> 180 | E16: =IF(OR($A16="",$B16=0),"",$C16/$B16) -> 0
A17: =IF('Budget Setup'!A20="","",'Budget Setup'!A20) -> Phone & internet | B17: =IF($A17="","",'Budget Setup'!B20) -> 95 | C17: =IF($A17="","",SUMIFS(Transactions!$D$6:$D$305,Transactions!$C$6:$C$305,$A17,Transactions!$A$6:$A$305,">="&DATE($D$4,$B$4,1),Transactions!$A$6:$A$305,"<"&DATE($D$4,$B$4+1,1))) -> 0 | D17: =IF($A17="","",$B17-$C17) -> 95 | E17: =IF(OR($A17="",$B17=0),"",$C17/$B17) -> 0
A18: =IF('Budget Setup'!A21="","",'Budget Setup'!A21) -> Insurance | B18: =IF($A18="","",'Budget Setup'!B21) -> 140 | C18: =IF($A18="","",SUMIFS(Transactions!$D$6:$D$305,Transactions!$C$6:$C$305,$A18,Transactions!$A$6:$A$305,">="&DATE($D$4,$B$4,1),Transactions!$A$6:$A$305,"<"&DATE($D$4,$B$4+1,1))) -> 0 | D18: =IF($A18="","",$B18-$C18) -> 140 | E18: =IF(OR($A18="",$B18=0),"",$C18/$B18) -> 0
A19: =IF('Budget Setup'!A22="","",'Budget Setup'!A22) -> Health & fitness | B19: =IF($A19="","",'Budget Setup'!B22) -> 90 | C19: =IF($A19="","",SUMIFS(Transactions!$D$6:$D$305,Transactions!$C$6:$C$305,$A19,Transactions!$A$6:$A$305,">="&DATE($D$4,$B$4,1),Transactions!$A$6:$A$305,"<"&DATE($D$4,$B$4+1,1))) -> 0 | D19: =IF($A19="","",$B19-$C19) -> 90 | E19: =IF(OR($A19="",$B19=0),"",$C19/$B19) -> 0
A20: =IF('Budget Setup'!A23="","",'Budget Setup'!A23) -> Entertainment | B20: =IF($A20="","",'Budget Setup'!B23) -> 120 | C20: =IF($A20="","",SUMIFS(Transactions!$D$6:$D$305,Transactions!$C$6:$C$305,$A20,Transactions!$A$6:$A$305,">="&DATE($D$4,$B$4,1),Transactions!$A$6:$A$305,"<"&DATE($D$4,$B$4+1,1))) -> 0 | D20: =IF($A20="","",$B20-$C20) -> 120 | E20: =IF(OR($A20="",$B20=0),"",$C20/$B20) -> 0
A21: =IF('Budget Setup'!A24="","",'Budget Setup'!A24) -> Subscriptions | B21: =IF($A21="","",'Budget Setup'!B24) -> 60 | C21: =IF($A21="","",SUMIFS(Transactions!$D$6:$D$305,Transactions!$C$6:$C$305,$A21,Transactions!$A$6:$A$305,">="&DATE($D$4,$B$4,1),Transactions!$A$6:$A$305,"<"&DATE($D$4,$B$4+1,1))) -> 0 | D21: =IF($A21="","",$B21-$C21) -> 60 | E21: =IF(OR($A21="",$B21=0),"",$C21/$B21) -> 0
A22: =IF('Budget Setup'!A25="","",'Budget Setup'!A25) -> Shopping | B22: =IF($A22="","",'Budget Setup'!B25) -> 150 | C22: =IF($A22="","",SUMIFS(Transactions!$D$6:$D$305,Transactions!$C$6:$C$305,$A22,Transactions!$A$6:$A$305,">="&DATE($D$4,$B$4,1),Transactions!$A$6:$A$305,"<"&DATE($D$4,$B$4+1,1))) -> 0 | D22: =IF($A22="","",$B22-$C22) -> 150 | E22: =IF(OR($A22="",$B22=0),"",$C22/$B22) -> 0
A23: =IF('Budget Setup'!A26="","",'Budget Setup'!A26) -> Personal care | B23: =IF($A23="","",'Budget Setup'!B26) -> 70 | C23: =IF($A23="","",SUMIFS(Transactions!$D$6:$D$305,Transactions!$C$6:$C$305,$A23,Transactions!$A$6:$A$305,">="&DATE($D$4,$B$4,1),Transactions!$A$6:$A$305,"<"&DATE($D$4,$B$4+1,1))) -> 0 | D23: =IF($A23="","",$B23-$C23) -> 70 | E23: =IF(OR($A23="",$B23=0),"",$C23/$B23) -> 0
... A31: =IF('Budget Setup'!A34="","",'Budget Setup'!A34) | B31: =IF($A31="","",'Budget Setup'!B34) | C31: =IF($A31="","",SUMIFS(Transactions!$D$6:$D$305,Transactions!$C$6:$C$305,$A31,Transactions!$A$6:$A$305,">="&DATE($D$4,$B$4,1),Transactions!$A$6:$A$305,"<"&DATE($D$4,$B$4+1,1))) | D31: =IF($A31="","",$B31-$C31) | E31: =IF(OR($A31="",$B31=0),"",$C31/$B31)

Sheet Year Overview
A1: Year Overview
A2: Twelve months at a glance — totals, trend, and a category heatmap.
A4: Year | B4: 2026
A6: Spending by month
A7: Month | B7: Spent | C7: % of budget
A8: Jan | B8: =SUMIFS(Transactions!$D$6:$D$305,Transactions!$A$6:$A$305,">="&DATE($B$4,1,1),Transactions!$A$6:$A$305,"<"&DATE($B$4,2,1)) -> 0 | C8: =IF('Budget Setup'!$B$36=0,"",$B8/'Budget Setup'!$B$36) -> 0
A9: Feb | B9: =SUMIFS(Transactions!$D$6:$D$305,Transactions!$A$6:$A$305,">="&DATE($B$4,2,1),Transactions!$A$6:$A$305,"<"&DATE($B$4,3,1)) -> 0 | C9: =IF('Budget Setup'!$B$36=0,"",$B9/'Budget Setup'!$B$36) -> 0
A10: Mar | B10: =SUMIFS(Transactions!$D$6:$D$305,Transactions!$A$6:$A$305,">="&DATE($B$4,3,1),Transactions!$A$6:$A$305,"<"&DATE($B$4,4,1)) -> 0 | C10: =IF('Budget Setup'!$B$36=0,"",$B10/'Budget Setup'!$B$36) -> 0
A11: Apr | B11: =SUMIFS(Transactions!$D$6:$D$305,Transactions!$A$6:$A$305,">="&DATE($B$4,4,1),Transactions!$A$6:$A$305,"<"&DATE($B$4,5,1)) -> 0 | C11: =IF('Budget Setup'!$B$36=0,"",$B11/'Budget Setup'!$B$36) -> 0
A12: May | B12: =SUMIFS(Transactions!$D$6:$D$305,Transactions!$A$6:$A$305,">="&DATE($B$4,5,1),Transactions!$A$6:$A$305,"<"&DATE($B$4,6,1)) -> 0 | C12: =IF('Budget Setup'!$B$36=0,"",$B12/'Budget Setup'!$B$36) -> 0
A13: Jun | B13: =SUMIFS(Transactions!$D$6:$D$305,Transactions!$A$6:$A$305,">="&DATE($B$4,6,1),Transactions!$A$6:$A$305,"<"&DATE($B$4,7,1)) -> 0 | C13: =IF('Budget Setup'!$B$36=0,"",$B13/'Budget Setup'!$B$36) -> 0
A14: Jul | B14: =SUMIFS(Transactions!$D$6:$D$305,Transactions!$A$6:$A$305,">="&DATE($B$4,7,1),Transactions!$A$6:$A$305,"<"&DATE($B$4,8,1)) -> 1873.5 | C14: =IF('Budget Setup'!$B$36=0,"",$B14/'Budget Setup'!$B$36) -> 0.42053872
A15: Aug | B15: =SUMIFS(Transactions!$D$6:$D$305,Transactions!$A$6:$A$305,">="&DATE($B$4,8,1),Transactions!$A$6:$A$305,"<"&DATE($B$4,9,1)) -> 1783.5 | C15: =IF('Budget Setup'!$B$36=0,"",$B15/'Budget Setup'!$B$36) -> 0.4003367
A16: Sep | B16: =SUMIFS(Transactions!$D$6:$D$305,Transactions!$A$6:$A$305,">="&DATE($B$4,9,1),Transactions!$A$6:$A$305,"<"&DATE($B$4,10,1)) -> 0 | C16: =IF('Budget Setup'!$B$36=0,"",$B16/'Budget Setup'!$B$36) -> 0
A17: Oct | B17: =SUMIFS(Transactions!$D$6:$D$305,Transactions!$A$6:$A$305,">="&DATE($B$4,10,1),Transactions!$A$6:$A$305,"<"&DATE($B$4,11,1)) -> 0 | C17: =IF('Budget Setup'!$B$36=0,"",$B17/'Budget Setup'!$B$36) -> 0
A18: Nov | B18: =SUMIFS(Transactions!$D$6:$D$305,Transactions!$A$6:$A$305,">="&DATE($B$4,11,1),Transactions!$A$6:$A$305,"<"&DATE($B$4,12,1)) -> 0 | C18: =IF('Budget Setup'!$B$36=0,"",$B18/'Budget Setup'!$B$36) -> 0
A19: Dec | B19: =SUMIFS(Transactions!$D$6:$D$305,Transactions!$A$6:$A$305,">="&DATE($B$4,12,1),Transactions!$A$6:$A$305,"<"&DATE($B$4,13,1)) -> 0 | C19: =IF('Budget Setup'!$B$36=0,"",$B19/'Budget Setup'!$B$36) -> 0
A20: Year total | B20: =SUM(B8:B19) -> 3657
A24: Category × month heatmap | E24: Darker = more spent. Spot the patterns.
A25: Category | B25: Jan | C25: Feb | D25: Mar | E25: Apr | F25: May | G25: Jun | H25: Jul | I25: Aug | J25: Sep | K25: Oct | L25: Nov | M25: Dec
A26: =IF('Budget Setup'!A15="","",'Budget Setup'!A15) -> Housing | B26: =IF($A26="","",SUMIFS(Transactions!$D$6:$D$305,Transactions!$C$6:$C$305,$A26,Transactions!$A$6:$A$305,">="&DATE($B$4,COLUMN()-1,1),Transactions!$A$6:$A$305,"<"&DATE($B$4,COLUMN(),1))) -> 0 | C26: =IF($A26="","",SUMIFS(Transactions!$D$6:$D$305,Transactions!$C$6:$C$305,$A26,Transactions!$A$6:$A$305,">="&DATE($B$4,COLUMN()-1,1),Transactions!$A$6:$A$305,"<"&DATE($B$4,COLUMN(),1))) -> 0 | D26: =IF($A26="","",SUMIFS(Transactions!$D$6:$D$305,Transactions!$C$6:$C$305,$A26,Transactions!$A$6:$A$305,">="&DATE($B$4,COLUMN()-1,1),Transactions!$A$6:$A$305,"<"&DATE($B$4,COLUMN(),1))) -> 0 | E26: =IF($A26="","",SUMIFS(Transactions!$D$6:$D$305,Transactions!$C$6:$C$305,$A26,Transactions!$A$6:$A$305,">="&DATE($B$4,COLUMN()-1,1),Transactions!$A$6:$A$305,"<"&DATE($B$4,COLUMN(),1))) -> 0 | F26: =IF($A26="","",SUMIFS(Transactions!$D$6:$D$305,Transactions!$C$6:$C$305,$A26,Transactions!$A$6:$A$305,">="&DATE($B$4,COLUMN()-1,1),Transactions!$A$6:$A$305,"<"&DATE($B$4,COLUMN(),1))) -> 0 | G26: =IF($A26="","",SUMIFS(Transactions!$D$6:$D$305,Transactions!$C$6:$C$305,$A26,Transactions!$A$6:$A$305,">="&DATE($B$4,COLUMN()-1,1),Transactions!$A$6:$A$305,"<"&DATE($B$4,COLUMN(),1))) -> 0 | H26: =IF($A26="","",SUMIFS(Transactions!$D$6:$D$305,Transactions!$C$6:$C$305,$A26,Transactions!$A$6:$A$305,">="&DATE($B$4,COLUMN()-1,1),Transactions!$A$6:$A$305,"<"&DATE($B$4,COLUMN(),1))) -> 1600 | I26: =IF($A26="","",SUMIFS(Transactions!$D$6:$D$305,Transactions!$C$6:$C$305,$A26,Transactions!$A$6:$A$305,">="&DATE($B$4,COLUMN()-1,1),Transactions!$A$6:$A$305,"<"&DATE($B$4,COLUMN(),1))) -> 1600 | ... M26: =IF($A26="","",SUMIFS(Transactions!$D$6:$D$305,Transactions!$C$6:$C$305,$A26,Transactions!$A$6:$A$305,">="&DATE($B$4,COLUMN()-1,1),Transactions!$A$6:$A$305,"<"&DATE($B$4,COLUMN(),1))) -> 0
A27: =IF('Budget Setup'!A16="","",'Budget Setup'!A16) -> Groceries | B27: =IF($A27="","",SUMIFS(Transactions!$D$6:$D$305,Transactions!$C$6:$C$305,$A27,Transactions!$A$6:$A$305,">="&DATE($B$4,COLUMN()-1,1),Transactions!$A$6:$A$305,"<"&DATE($B$4,COLUMN(),1))) -> 0 | C27: =IF($A27="","",SUMIFS(Transactions!$D$6:$D$305,Transactions!$C$6:$C$305,$A27,Transactions!$A$6:$A$305,">="&DATE($B$4,COLUMN()-1,1),Transactions!$A$6:$A$305,"<"&DATE($B$4,COLUMN(),1))) -> 0 | D27: =IF($A27="","",SUMIFS(Transactions!$D$6:$D$305,Transactions!$C$6:$C$305,$A27,Transactions!$A$6:$A$305,">="&DATE($B$4,COLUMN()-1,1),Transactions!$A$6:$A$305,"<"&DATE($B$4,COLUMN(),1))) -> 0 | E27: =IF($A27="","",SUMIFS(Transactions!$D$6:$D$305,Transactions!$C$6:$C$305,$A27,Transactions!$A$6:$A$305,">="&DATE($B$4,COLUMN()-1,1),Transactions!$A$6:$A$305,"<"&DATE($B$4,COLUMN(),1))) -> 0 | F27: =IF($A27="","",SUMIFS(Transactions!$D$6:$D$305,Transactions!$C$6:$C$305,$A27,Transactions!$A$6:$A$305,">="&DATE($B$4,COLUMN()-1,1),Transactions!$A$6:$A$305,"<"&DATE($B$4,COLUMN(),1))) -> 0 | G27: =IF($A27="","",SUMIFS(Transactions!$D$6:$D$305,Transactions!$C$6:$C$305,$A27,Transactions!$A$6:$A$305,">="&DATE($B$4,COLUMN()-1,1),Transactions!$A$6:$A$305,"<"&DATE($B$4,COLUMN(),1))) -> 0 | H27: =IF($A27="","",SUMIFS(Transactions!$D$6:$D$305,Transactions!$C$6:$C$305,$A27,Transactions!$A$6:$A$305,">="&DATE($B$4,COLUMN()-1,1),Transactions!$A$6:$A$305,"<"&DATE($B$4,COLUMN(),1))) -> 184.5 | I27: =IF($A27="","",SUMIFS(Transactions!$D$6:$D$305,Transactions!$C$6:$C$305,$A27,Transactions!$A$6:$A$305,">="&DATE($B$4,COLUMN()-1,1),Transactions!$A$6:$A$305,"<"&DATE($B$4,COLUMN(),1))) -> 84.2 | ... M27: =IF($A27="","",SUMIFS(Transactions!$D$6:$D$305,Transactions!$C$6:$C$305,$A27,Transactions!$A$6:$A$305,">="&DATE($B$4,COLUMN()-1,1),Transactions!$A$6:$A$305,"<"&DATE($B$4,COLUMN(),1))) -> 0
A28: =IF('Budget Setup'!A17="","",'Budget Setup'!A17) -> Dining out | B28: =IF($A28="","",SUMIFS(Transactions!$D$6:$D$305,Transactions!$C$6:$C$305,$A28,Transactions!$A$6:$A$305,">="&DATE($B$4,COLUMN()-1,1),Transactions!$A$6:$A$305,"<"&DATE($B$4,COLUMN(),1))) -> 0 | C28: =IF($A28="","",SUMIFS(Transactions!$D$6:$D$305,Transactions!$C$6:$C$305,$A28,Transactions!$A$6:$A$305,">="&DATE($B$4,COLUMN()-1,1),Transactions!$A$6:$A$305,"<"&DATE($B$4,COLUMN(),1))) -> 0 | D28: =IF($A28="","",SUMIFS(Transactions!$D$6:$D$305,Transactions!$C$6:$C$305,$A28,Transactions!$A$6:$A$305,">="&DATE($B$4,COLUMN()-1,1),Transactions!$A$6:$A$305,"<"&DATE($B$4,COLUMN(),1))) -> 0 | E28: =IF($A28="","",SUMIFS(Transactions!$D$6:$D$305,Transactions!$C$6:$C$305,$A28,Transactions!$A$6:$A$305,">="&DATE($B$4,COLUMN()-1,1),Transactions!$A$6:$A$305,"<"&DATE($B$4,COLUMN(),1))) -> 0 | F28: =IF($A28="","",SUMIFS(Transactions!$D$6:$D$305,Transactions!$C$6:$C$305,$A28,Transactions!$A$6:$A$305,">="&DATE($B$4,COLUMN()-1,1),Transactions!$A$6:$A$305,"<"&DATE($B$4,COLUMN(),1))) -> 0 | G28: =IF($A28="","",SUMIFS(Transactions!$D$6:$D$305,Transactions!$C$6:$C$305,$A28,Transactions!$A$6:$A$305,">="&DATE($B$4,COLUMN()-1,1),Transactions!$A$6:$A$305,"<"&DATE($B$4,COLUMN(),1))) -> 0 | H28: =IF($A28="","",SUMIFS(Transactions!$D$6:$D$305,Transactions!$C$6:$C$305,$A28,Transactions!$A$6:$A$305,">="&DATE($B$4,COLUMN()-1,1),Transactions!$A$6:$A$305,"<"&DATE($B$4,COLUMN(),1))) -> 0 | I28: =IF($A28="","",SUMIFS(Transactions!$D$6:$D$305,Transactions!$C$6:$C$305,$A28,Transactions!$A$6:$A$305,">="&DATE($B$4,COLUMN()-1,1),Transactions!$A$6:$A$305,"<"&DATE($B$4,COLUMN(),1))) -> 56.8 | ... M28: =IF($A28="","",SUMIFS(Transactions!$D$6:$D$305,Transactions!$C$6:$C$305,$A28,Transactions!$A$6:$A$305,">="&DATE($B$4,COLUMN()-1,1),Transactions!$A$6:$A$305,"<"&DATE($B$4,COLUMN(),1))) -> 0
A29: =IF('Budget Setup'!A18="","",'Budget Setup'!A18) -> Transport | B29: =IF($A29="","",SUMIFS(Transactions!$D$6:$D$305,Transactions!$C$6:$C$305,$A29,Transactions!$A$6:$A$305,">="&DATE($B$4,COLUMN()-1,1),Transactions!$A$6:$A$305,"<"&DATE($B$4,COLUMN(),1))) -> 0 | C29: =IF($A29="","",SUMIFS(Transactions!$D$6:$D$305,Transactions!$C$6:$C$305,$A29,Transactions!$A$6:$A$305,">="&DATE($B$4,COLUMN()-1,1),Transactions!$A$6:$A$305,"<"&DATE($B$4,COLUMN(),1))) -> 0 | D29: =IF($A29="","",SUMIFS(Transactions!$D$6:$D$305,Transactions!$C$6:$C$305,$A29,Transactions!$A$6:$A$305,">="&DATE($B$4,COLUMN()-1,1),Transactions!$A$6:$A$305,"<"&DATE($B$4,COLUMN(),1))) -> 0 | E29: =IF($A29="","",SUMIFS(Transactions!$D$6:$D$305,Transactions!$C$6:$C$305,$A29,Transactions!$A$6:$A$305,">="&DATE($B$4,COLUMN()-1,1),Transactions!$A$6:$A$305,"<"&DATE($B$4,COLUMN(),1))) -> 0 | F29: =IF($A29="","",SUMIFS(Transactions!$D$6:$D$305,Transactions!$C$6:$C$305,$A29,Transactions!$A$6:$A$305,">="&DATE($B$4,COLUMN()-1,1),Transactions!$A$6:$A$305,"<"&DATE($B$4,COLUMN(),1))) -> 0 | G29: =IF($A29="","",SUMIFS(Transactions!$D$6:$D$305,Transactions!$C$6:$C$305,$A29,Transactions!$A$6:$A$305,">="&DATE($B$4,COLUMN()-1,1),Transactions!$A$6:$A$305,"<"&DATE($B$4,COLUMN(),1))) -> 0 | H29: =IF($A29="","",SUMIFS(Transactions!$D$6:$D$305,Transactions!$C$6:$C$305,$A29,Transactions!$A$6:$A$305,">="&DATE($B$4,COLUMN()-1,1),Transactions!$A$6:$A$305,"<"&DATE($B$4,COLUMN(),1))) -> 0 | I29: =IF($A29="","",SUMIFS(Transactions!$D$6:$D$305,Transactions!$C$6:$C$305,$A29,Transactions!$A$6:$A$305,">="&DATE($B$4,COLUMN()-1,1),Transactions!$A$6:$A$305,"<"&DATE($B$4,COLUMN(),1))) -> 42.5 | ... M29: =IF($A29="","",SUMIFS(Transactions!$D$6:$D$305,Transactions!$C$6:$C$305,$A29,Transactions!$A$6:$A$305,">="&DATE($B$4,COLUMN()-1,1),Transactions!$A$6:$A$305,"<"&DATE($B$4,COLUMN(),1))) -> 0
A30: =IF('Budget Setup'!A19="","",'Budget Setup'!A19) -> Utilities | B30: =IF($A30="","",SUMIFS(Transactions!$D$6:$D$305,Transactions!$C$6:$C$305,$A30,Transactions!$A$6:$A$305,">="&DATE($B$4,COLUMN()-1,1),Transactions!$A$6:$A$305,"<"&DATE($B$4,COLUMN(),1))) -> 0 | C30: =IF($A30="","",SUMIFS(Transactions!$D$6:$D$305,Transactions!$C$6:$C$305,$A30,Transactions!$A$6:$A$305,">="&DATE($B$4,COLUMN()-1,1),Transactions!$A$6:$A$305,"<"&DATE($B$4,COLUMN(),1))) -> 0 | D30: =IF($A30="","",SUMIFS(Transactions!$D$6:$D$305,Transactions!$C$6:$C$305,$A30,Transactions!$A$6:$A$305,">="&DATE($B$4,COLUMN()-1,1),Transactions!$A$6:$A$305,"<"&DATE($B$4,COLUMN(),1))) -> 0 | E30: =IF($A30="","",SUMIFS(Transactions!$D$6:$D$305,Transactions!$C$6:$C$305,$A30,Transactions!$A$6:$A$305,">="&DATE($B$4,COLUMN()-1,1),Transactions!$A$6:$A$305,"<"&DATE($B$4,COLUMN(),1))) -> 0 | F30: =IF($A30="","",SUMIFS(Transactions!$D$6:$D$305,Transactions!$C$6:$C$305,$A30,Transactions!$A$6:$A$305,">="&DATE($B$4,COLUMN()-1,1),Transactions!$A$6:$A$305,"<"&DATE($B$4,COLUMN(),1))) -> 0 | G30: =IF($A30="","",SUMIFS(Transactions!$D$6:$D$305,Transactions!$C$6:$C$305,$A30,Transactions!$A$6:$A$305,">="&DATE($B$4,COLUMN()-1,1),Transactions!$A$6:$A$305,"<"&DATE($B$4,COLUMN(),1))) -> 0 | H30: =IF($A30="","",SUMIFS(Transactions!$D$6:$D$305,Transactions!$C$6:$C$305,$A30,Transactions!$A$6:$A$305,">="&DATE($B$4,COLUMN()-1,1),Transactions!$A$6:$A$305,"<"&DATE($B$4,COLUMN(),1))) -> 0 | I30: =IF($A30="","",SUMIFS(Transactions!$D$6:$D$305,Transactions!$C$6:$C$305,$A30,Transactions!$A$6:$A$305,">="&DATE($B$4,COLUMN()-1,1),Transactions!$A$6:$A$305,"<"&DATE($B$4,COLUMN(),1))) -> 0 | ... M30: =IF($A30="","",SUMIFS(Transactions!$D$6:$D$305,Transactions!$C$6:$C$305,$A30,Transactions!$A$6:$A$305,">="&DATE($B$4,COLUMN()-1,1),Transactions!$A$6:$A$305,"<"&DATE($B$4,COLUMN(),1))) -> 0
A31: =IF('Budget Setup'!A20="","",'Budget Setup'!A20) -> Phone & internet | B31: =IF($A31="","",SUMIFS(Transactions!$D$6:$D$305,Transactions!$C$6:$C$305,$A31,Transactions!$A$6:$A$305,">="&DATE($B$4,COLUMN()-1,1),Transactions!$A$6:$A$305,"<"&DATE($B$4,COLUMN(),1))) -> 0 | C31: =IF($A31="","",SUMIFS(Transactions!$D$6:$D$305,Transactions!$C$6:$C$305,$A31,Transactions!$A$6:$A$305,">="&DATE($B$4,COLUMN()-1,1),Transactions!$A$6:$A$305,"<"&DATE($B$4,COLUMN(),1))) -> 0 | D31: =IF($A31="","",SUMIFS(Transactions!$D$6:$D$305,Transactions!$C$6:$C$305,$A31,Transactions!$A$6:$A$305,">="&DATE($B$4,COLUMN()-1,1),Transactions!$A$6:$A$305,"<"&DATE($B$4,COLUMN(),1))) -> 0 | E31: =IF($A31="","",SUMIFS(Transactions!$D$6:$D$305,Transactions!$C$6:$C$305,$A31,Transactions!$A$6:$A$305,">="&DATE($B$4,COLUMN()-1,1),Transactions!$A$6:$A$305,"<"&DATE($B$4,COLUMN(),1))) -> 0 | F31: =IF($A31="","",SUMIFS(Transactions!$D$6:$D$305,Transactions!$C$6:$C$305,$A31,Transactions!$A$6:$A$305,">="&DATE($B$4,COLUMN()-1,1),Transactions!$A$6:$A$305,"<"&DATE($B$4,COLUMN(),1))) -> 0 | G31: =IF($A31="","",SUMIFS(Transactions!$D$6:$D$305,Transactions!$C$6:$C$305,$A31,Transactions!$A$6:$A$305,">="&DATE($B$4,COLUMN()-1,1),Transactions!$A$6:$A$305,"<"&DATE($B$4,COLUMN(),1))) -> 0 | H31: =IF($A31="","",SUMIFS(Transactions!$D$6:$D$305,Transactions!$C$6:$C$305,$A31,Transactions!$A$6:$A$305,">="&DATE($B$4,COLUMN()-1,1),Transactions!$A$6:$A$305,"<"&DATE($B$4,COLUMN(),1))) -> 0 | I31: =IF($A31="","",SUMIFS(Transactions!$D$6:$D$305,Transactions!$C$6:$C$305,$A31,Transactions!$A$6:$A$305,">="&DATE($B$4,COLUMN()-1,1),Transactions!$A$6:$A$305,"<"&DATE($B$4,COLUMN(),1))) -> 0 | ... M31: =IF($A31="","",SUMIFS(Transactions!$D$6:$D$305,Transactions!$C$6:$C$305,$A31,Transactions!$A$6:$A$305,">="&DATE($B$4,COLUMN()-1,1),Transactions!$A$6:$A$305,"<"&DATE($B$4,COLUMN(),1))) -> 0
A32: =IF('Budget Setup'!A21="","",'Budget Setup'!A21) -> Insurance | B32: =IF($A32="","",SUMIFS(Transactions!$D$6:$D$305,Transactions!$C$6:$C$305,$A32,Transactions!$A$6:$A$305,">="&DATE($B$4,COLUMN()-1,1),Transactions!$A$6:$A$305,"<"&DATE($B$4,COLUMN(),1))) -> 0 | C32: =IF($A32="","",SUMIFS(Transactions!$D$6:$D$305,Transactions!$C$6:$C$305,$A32,Transactions!$A$6:$A$305,">="&DATE($B$4,COLUMN()-1,1),Transactions!$A$6:$A$305,"<"&DATE($B$4,COLUMN(),1))) -> 0 | D32: =IF($A32="","",SUMIFS(Transactions!$D$6:$D$305,Transactions!$C$6:$C$305,$A32,Transactions!$A$6:$A$305,">="&DATE($B$4,COLUMN()-1,1),Transactions!$A$6:$A$305,"<"&DATE($B$4,COLUMN(),1))) -> 0 | E32: =IF($A32="","",SUMIFS(Transactions!$D$6:$D$305,Transactions!$C$6:$C$305,$A32,Transactions!$A$6:$A$305,">="&DATE($B$4,COLUMN()-1,1),Transactions!$A$6:$A$305,"<"&DATE($B$4,COLUMN(),1))) -> 0 | F32: =IF($A32="","",SUMIFS(Transactions!$D$6:$D$305,Transactions!$C$6:$C$305,$A32,Transactions!$A$6:$A$305,">="&DATE($B$4,COLUMN()-1,1),Transactions!$A$6:$A$305,"<"&DATE($B$4,COLUMN(),1))) -> 0 | G32: =IF($A32="","",SUMIFS(Transactions!$D$6:$D$305,Transactions!$C$6:$C$305,$A32,Transactions!$A$6:$A$305,">="&DATE($B$4,COLUMN()-1,1),Transactions!$A$6:$A$305,"<"&DATE($B$4,COLUMN(),1))) -> 0 | H32: =IF($A32="","",SUMIFS(Transactions!$D$6:$D$305,Transactions!$C$6:$C$305,$A32,Transactions!$A$6:$A$305,">="&DATE($B$4,COLUMN()-1,1),Transactions!$A$6:$A$305,"<"&DATE($B$4,COLUMN(),1))) -> 0 | I32: =IF($A32="","",SUMIFS(Transactions!$D$6:$D$305,Transactions!$C$6:$C$305,$A32,Transactions!$A$6:$A$305,">="&DATE($B$4,COLUMN()-1,1),Transactions!$A$6:$A$305,"<"&DATE($B$4,COLUMN(),1))) -> 0 | ... M32: =IF($A32="","",SUMIFS(Transactions!$D$6:$D$305,Transactions!$C$6:$C$305,$A32,Transactions!$A$6:$A$305,">="&DATE($B$4,COLUMN()-1,1),Transactions!$A$6:$A$305,"<"&DATE($B$4,COLUMN(),1))) -> 0
A33: =IF('Budget Setup'!A22="","",'Budget Setup'!A22) -> Health & fitness | B33: =IF($A33="","",SUMIFS(Transactions!$D$6:$D$305,Transactions!$C$6:$C$305,$A33,Transactions!$A$6:$A$305,">="&DATE($B$4,COLUMN()-1,1),Transactions!$A$6:$A$305,"<"&DATE($B$4,COLUMN(),1))) -> 0 | C33: =IF($A33="","",SUMIFS(Transactions!$D$6:$D$305,Transactions!$C$6:$C$305,$A33,Transactions!$A$6:$A$305,">="&DATE($B$4,COLUMN()-1,1),Transactions!$A$6:$A$305,"<"&DATE($B$4,COLUMN(),1))) -> 0 | D33: =IF($A33="","",SUMIFS(Transactions!$D$6:$D$305,Transactions!$C$6:$C$305,$A33,Transactions!$A$6:$A$305,">="&DATE($B$4,COLUMN()-1,1),Transactions!$A$6:$A$305,"<"&DATE($B$4,COLUMN(),1))) -> 0 | E33: =IF($A33="","",SUMIFS(Transactions!$D$6:$D$305,Transactions!$C$6:$C$305,$A33,Transactions!$A$6:$A$305,">="&DATE($B$4,COLUMN()-1,1),Transactions!$A$6:$A$305,"<"&DATE($B$4,COLUMN(),1))) -> 0 | F33: =IF($A33="","",SUMIFS(Transactions!$D$6:$D$305,Transactions!$C$6:$C$305,$A33,Transactions!$A$6:$A$305,">="&DATE($B$4,COLUMN()-1,1),Transactions!$A$6:$A$305,"<"&DATE($B$4,COLUMN(),1))) -> 0 | G33: =IF($A33="","",SUMIFS(Transactions!$D$6:$D$305,Transactions!$C$6:$C$305,$A33,Transactions!$A$6:$A$305,">="&DATE($B$4,COLUMN()-1,1),Transactions!$A$6:$A$305,"<"&DATE($B$4,COLUMN(),1))) -> 0 | H33: =IF($A33="","",SUMIFS(Transactions!$D$6:$D$305,Transactions!$C$6:$C$305,$A33,Transactions!$A$6:$A$305,">="&DATE($B$4,COLUMN()-1,1),Transactions!$A$6:$A$305,"<"&DATE($B$4,COLUMN(),1))) -> 0 | I33: =IF($A33="","",SUMIFS(Transactions!$D$6:$D$305,Transactions!$C$6:$C$305,$A33,Transactions!$A$6:$A$305,">="&DATE($B$4,COLUMN()-1,1),Transactions!$A$6:$A$305,"<"&DATE($B$4,COLUMN(),1))) -> 0 | ... M33: =IF($A33="","",SUMIFS(Transactions!$D$6:$D$305,Transactions!$C$6:$C$305,$A33,Transactions!$A$6:$A$305,">="&DATE($B$4,COLUMN()-1,1),Transactions!$A$6:$A$305,"<"&DATE($B$4,COLUMN(),1))) -> 0
A34: =IF('Budget Setup'!A23="","",'Budget Setup'!A23) -> Entertainment | B34: =IF($A34="","",SUMIFS(Transactions!$D$6:$D$305,Transactions!$C$6:$C$305,$A34,Transactions!$A$6:$A$305,">="&DATE($B$4,COLUMN()-1,1),Transactions!$A$6:$A$305,"<"&DATE($B$4,COLUMN(),1))) -> 0 | C34: =IF($A34="","",SUMIFS(Transactions!$D$6:$D$305,Transactions!$C$6:$C$305,$A34,Transactions!$A$6:$A$305,">="&DATE($B$4,COLUMN()-1,1),Transactions!$A$6:$A$305,"<"&DATE($B$4,COLUMN(),1))) -> 0 | D34: =IF($A34="","",SUMIFS(Transactions!$D$6:$D$305,Transactions!$C$6:$C$305,$A34,Transactions!$A$6:$A$305,">="&DATE($B$4,COLUMN()-1,1),Transactions!$A$6:$A$305,"<"&DATE($B$4,COLUMN(),1))) -> 0 | E34: =IF($A34="","",SUMIFS(Transactions!$D$6:$D$305,Transactions!$C$6:$C$305,$A34,Transactions!$A$6:$A$305,">="&DATE($B$4,COLUMN()-1,1),Transactions!$A$6:$A$305,"<"&DATE($B$4,COLUMN(),1))) -> 0 | F34: =IF($A34="","",SUMIFS(Transactions!$D$6:$D$305,Transactions!$C$6:$C$305,$A34,Transactions!$A$6:$A$305,">="&DATE($B$4,COLUMN()-1,1),Transactions!$A$6:$A$305,"<"&DATE($B$4,COLUMN(),1))) -> 0 | G34: =IF($A34="","",SUMIFS(Transactions!$D$6:$D$305,Transactions!$C$6:$C$305,$A34,Transactions!$A$6:$A$305,">="&DATE($B$4,COLUMN()-1,1),Transactions!$A$6:$A$305,"<"&DATE($B$4,COLUMN(),1))) -> 0 | H34: =IF($A34="","",SUMIFS(Transactions!$D$6:$D$305,Transactions!$C$6:$C$305,$A34,Transactions!$A$6:$A$305,">="&DATE($B$4,COLUMN()-1,1),Transactions!$A$6:$A$305,"<"&DATE($B$4,COLUMN(),1))) -> 89 | I34: =IF($A34="","",SUMIFS(Transactions!$D$6:$D$305,Transactions!$C$6:$C$305,$A34,Transactions!$A$6:$A$305,">="&DATE($B$4,COLUMN()-1,1),Transactions!$A$6:$A$305,"<"&DATE($B$4,COLUMN(),1))) -> 0 | ... M34: =IF($A34="","",SUMIFS(Transactions!$D$6:$D$305,Transactions!$C$6:$C$305,$A34,Transactions!$A$6:$A$305,">="&DATE($B$4,COLUMN()-1,1),Transactions!$A$6:$A$305,"<"&DATE($B$4,COLUMN(),1))) -> 0
A35: =IF('Budget Setup'!A24="","",'Budget Setup'!A24) -> Subscriptions | B35: =IF($A35="","",SUMIFS(Transactions!$D$6:$D$305,Transactions!$C$6:$C$305,$A35,Transactions!$A$6:$A$305,">="&DATE($B$4,COLUMN()-1,1),Transactions!$A$6:$A$305,"<"&DATE($B$4,COLUMN(),1))) -> 0 | C35: =IF($A35="","",SUMIFS(Transactions!$D$6:$D$305,Transactions!$C$6:$C$305,$A35,Transactions!$A$6:$A$305,">="&DATE($B$4,COLUMN()-1,1),Transactions!$A$6:$A$305,"<"&DATE($B$4,COLUMN(),1))) -> 0 | D35: =IF($A35="","",SUMIFS(Transactions!$D$6:$D$305,Transactions!$C$6:$C$305,$A35,Transactions!$A$6:$A$305,">="&DATE($B$4,COLUMN()-1,1),Transactions!$A$6:$A$305,"<"&DATE($B$4,COLUMN(),1))) -> 0 | E35: =IF($A35="","",SUMIFS(Transactions!$D$6:$D$305,Transactions!$C$6:$C$305,$A35,Transactions!$A$6:$A$305,">="&DATE($B$4,COLUMN()-1,1),Transactions!$A$6:$A$305,"<"&DATE($B$4,COLUMN(),1))) -> 0 | F35: =IF($A35="","",SUMIFS(Transactions!$D$6:$D$305,Transactions!$C$6:$C$305,$A35,Transactions!$A$6:$A$305,">="&DATE($B$4,COLUMN()-1,1),Transactions!$A$6:$A$305,"<"&DATE($B$4,COLUMN(),1))) -> 0 | G35: =IF($A35="","",SUMIFS(Transactions!$D$6:$D$305,Transactions!$C$6:$C$305,$A35,Transactions!$A$6:$A$305,">="&DATE($B$4,COLUMN()-1,1),Transactions!$A$6:$A$305,"<"&DATE($B$4,COLUMN(),1))) -> 0 | H35: =IF($A35="","",SUMIFS(Transactions!$D$6:$D$305,Transactions!$C$6:$C$305,$A35,Transactions!$A$6:$A$305,">="&DATE($B$4,COLUMN()-1,1),Transactions!$A$6:$A$305,"<"&DATE($B$4,COLUMN(),1))) -> 0 | I35: =IF($A35="","",SUMIFS(Transactions!$D$6:$D$305,Transactions!$C$6:$C$305,$A35,Transactions!$A$6:$A$305,">="&DATE($B$4,COLUMN()-1,1),Transactions!$A$6:$A$305,"<"&DATE($B$4,COLUMN(),1))) -> 0 | ... M35: =IF($A35="","",SUMIFS(Transactions!$D$6:$D$305,Transactions!$C$6:$C$305,$A35,Transactions!$A$6:$A$305,">="&DATE($B$4,COLUMN()-1,1),Transactions!$A$6:$A$305,"<"&DATE($B$4,COLUMN(),1))) -> 0
A36: =IF('Budget Setup'!A25="","",'Budget Setup'!A25) -> Shopping | B36: =IF($A36="","",SUMIFS(Transactions!$D$6:$D$305,Transactions!$C$6:$C$305,$A36,Transactions!$A$6:$A$305,">="&DATE($B$4,COLUMN()-1,1),Transactions!$A$6:$A$305,"<"&DATE($B$4,COLUMN(),1))) -> 0 | C36: =IF($A36="","",SUMIFS(Transactions!$D$6:$D$305,Transactions!$C$6:$C$305,$A36,Transactions!$A$6:$A$305,">="&DATE($B$4,COLUMN()-1,1),Transactions!$A$6:$A$305,"<"&DATE($B$4,COLUMN(),1))) -> 0 | D36: =IF($A36="","",SUMIFS(Transactions!$D$6:$D$305,Transactions!$C$6:$C$305,$A36,Transactions!$A$6:$A$305,">="&DATE($B$4,COLUMN()-1,1),Transactions!$A$6:$A$305,"<"&DATE($B$4,COLUMN(),1))) -> 0 | E36: =IF($A36="","",SUMIFS(Transactions!$D$6:$D$305,Transactions!$C$6:$C$305,$A36,Transactions!$A$6:$A$305,">="&DATE($B$4,COLUMN()-1,1),Transactions!$A$6:$A$305,"<"&DATE($B$4,COLUMN(),1))) -> 0 | F36: =IF($A36="","",SUMIFS(Transactions!$D$6:$D$305,Transactions!$C$6:$C$305,$A36,Transactions!$A$6:$A$305,">="&DATE($B$4,COLUMN()-1,1),Transactions!$A$6:$A$305,"<"&DATE($B$4,COLUMN(),1))) -> 0 | G36: =IF($A36="","",SUMIFS(Transactions!$D$6:$D$305,Transactions!$C$6:$C$305,$A36,Transactions!$A$6:$A$305,">="&DATE($B$4,COLUMN()-1,1),Transactions!$A$6:$A$305,"<"&DATE($B$4,COLUMN(),1))) -> 0 | H36: =IF($A36="","",SUMIFS(Transactions!$D$6:$D$305,Transactions!$C$6:$C$305,$A36,Transactions!$A$6:$A$305,">="&DATE($B$4,COLUMN()-1,1),Transactions!$A$6:$A$305,"<"&DATE($B$4,COLUMN(),1))) -> 0 | I36: =IF($A36="","",SUMIFS(Transactions!$D$6:$D$305,Transactions!$C$6:$C$305,$A36,Transactions!$A$6:$A$305,">="&DATE($B$4,COLUMN()-1,1),Transactions!$A$6:$A$305,"<"&DATE($B$4,COLUMN(),1))) -> 0 | ... M36: =IF($A36="","",SUMIFS(Transactions!$D$6:$D$305,Transactions!$C$6:$C$305,$A36,Transactions!$A$6:$A$305,">="&DATE($B$4,COLUMN()-1,1),Transactions!$A$6:$A$305,"<"&DATE($B$4,COLUMN(),1))) -> 0
A37: =IF('Budget Setup'!A26="","",'Budget Setup'!A26) -> Personal care | B37: =IF($A37="","",SUMIFS(Transactions!$D$6:$D$305,Transactions!$C$6:$C$305,$A37,Transactions!$A$6:$A$305,">="&DATE($B$4,COLUMN()-1,1),Transactions!$A$6:$A$305,"<"&DATE($B$4,COLUMN(),1))) -> 0 | C37: =IF($A37="","",SUMIFS(Transactions!$D$6:$D$305,Transactions!$C$6:$C$305,$A37,Transactions!$A$6:$A$305,">="&DATE($B$4,COLUMN()-1,1),Transactions!$A$6:$A$305,"<"&DATE($B$4,COLUMN(),1))) -> 0 | D37: =IF($A37="","",SUMIFS(Transactions!$D$6:$D$305,Transactions!$C$6:$C$305,$A37,Transactions!$A$6:$A$305,">="&DATE($B$4,COLUMN()-1,1),Transactions!$A$6:$A$305,"<"&DATE($B$4,COLUMN(),1))) -> 0 | E37: =IF($A37="","",SUMIFS(Transactions!$D$6:$D$305,Transactions!$C$6:$C$305,$A37,Transactions!$A$6:$A$305,">="&DATE($B$4,COLUMN()-1,1),Transactions!$A$6:$A$305,"<"&DATE($B$4,COLUMN(),1))) -> 0 | F37: =IF($A37="","",SUMIFS(Transactions!$D$6:$D$305,Transactions!$C$6:$C$305,$A37,Transactions!$A$6:$A$305,">="&DATE($B$4,COLUMN()-1,1),Transactions!$A$6:$A$305,"<"&DATE($B$4,COLUMN(),1))) -> 0 | G37: =IF($A37="","",SUMIFS(Transactions!$D$6:$D$305,Transactions!$C$6:$C$305,$A37,Transactions!$A$6:$A$305,">="&DATE($B$4,COLUMN()-1,1),Transactions!$A$6:$A$305,"<"&DATE($B$4,COLUMN(),1))) -> 0 | H37: =IF($A37="","",SUMIFS(Transactions!$D$6:$D$305,Transactions!$C$6:$C$305,$A37,Transactions!$A$6:$A$305,">="&DATE($B$4,COLUMN()-1,1),Transactions!$A$6:$A$305,"<"&DATE($B$4,COLUMN(),1))) -> 0 | I37: =IF($A37="","",SUMIFS(Transactions!$D$6:$D$305,Transactions!$C$6:$C$305,$A37,Transactions!$A$6:$A$305,">="&DATE($B$4,COLUMN()-1,1),Transactions!$A$6:$A$305,"<"&DATE($B$4,COLUMN(),1))) -> 0 | ... M37: =IF($A37="","",SUMIFS(Transactions!$D$6:$D$305,Transactions!$C$6:$C$305,$A37,Transactions!$A$6:$A$305,">="&DATE($B$4,COLUMN()-1,1),Transactions!$A$6:$A$305,"<"&DATE($B$4,COLUMN(),1))) -> 0
... A45: =IF('Budget Setup'!A34="","",'Budget Setup'!A34) | B45: =IF($A45="","",SUMIFS(Transactions!$D$6:$D$305,Transactions!$C$6:$C$305,$A45,Transactions!$A$6:$A$305,">="&DATE($B$4,COLUMN()-1,1),Transactions!$A$6:$A$305,"<"&DATE($B$4,COLUMN(),1))) | C45: =IF($A45="","",SUMIFS(Transactions!$D$6:$D$305,Transactions!$C$6:$C$305,$A45,Transactions!$A$6:$A$305,">="&DATE($B$4,COLUMN()-1,1),Transactions!$A$6:$A$305,"<"&DATE($B$4,COLUMN(),1))) | D45: =IF($A45="","",SUMIFS(Transactions!$D$6:$D$305,Transactions!$C$6:$C$305,$A45,Transactions!$A$6:$A$305,">="&DATE($B$4,COLUMN()-1,1),Transactions!$A$6:$A$305,"<"&DATE($B$4,COLUMN(),1))) | E45: =IF($A45="","",SUMIFS(Transactions!$D$6:$D$305,Transactions!$C$6:$C$305,$A45,Transactions!$A$6:$A$305,">="&DATE($B$4,COLUMN()-1,1),Transactions!$A$6:$A$305,"<"&DATE($B$4,COLUMN(),1))) | F45: =IF($A45="","",SUMIFS(Transactions!$D$6:$D$305,Transactions!$C$6:$C$305,$A45,Transactions!$A$6:$A$305,">="&DATE($B$4,COLUMN()-1,1),Transactions!$A$6:$A$305,"<"&DATE($B$4,COLUMN(),1))) | G45: =IF($A45="","",SUMIFS(Transactions!$D$6:$D$305,Transactions!$C$6:$C$305,$A45,Transactions!$A$6:$A$305,">="&DATE($B$4,COLUMN()-1,1),Transactions!$A$6:$A$305,"<"&DATE($B$4,COLUMN(),1))) | H45: =IF($A45="","",SUMIFS(Transactions!$D$6:$D$305,Transactions!$C$6:$C$305,$A45,Transactions!$A$6:$A$305,">="&DATE($B$4,COLUMN()-1,1),Transactions!$A$6:$A$305,"<"&DATE($B$4,COLUMN(),1))) | I45: =IF($A45="","",SUMIFS(Transactions!$D$6:$D$305,Transactions!$C$6:$C$305,$A45,Transactions!$A$6:$A$305,">="&DATE($B$4,COLUMN()-1,1),Transactions!$A$6:$A$305,"<"&DATE($B$4,COLUMN(),1))) | ... M45: =IF($A45="","",SUMIFS(Transactions!$D$6:$D$305,Transactions!$C$6:$C$305,$A45,Transactions!$A$6:$A$305,">="&DATE($B$4,COLUMN()-1,1),Transactions!$A$6:$A$305,"<"&DATE($B$4,COLUMN(),1)))

Sheet Savings Goals
A1: Savings Goals
A2: Set a target and a date — see exactly what to put away each month.
A4: Fill in the yellow columns. Months left, monthly needed, and progress calculate themselves.
A5: Goal | B5: Target | C5: Saved so far | D5: Target date | E5: Months left | F5: Monthly needed | G5: Progress
A6: Emergency fund | B6: 3000 | C6: 1150 | D6: 46387 | E6: =IF(OR($A6="",$D6=""),"",MAX(0,(YEAR($D6)-YEAR(TODAY()))*12+MONTH($D6)-MONTH(TODAY()))) -> 4 | F6: =IF(OR($A6="",$B6="",$D6=""),"",IF($E6=0,MAX(0,$B6-$C6),ROUND(MAX(0,$B6-$C6)/$E6,2))) -> 462.5 | G6: =IF(OR($A6="",$B6="",$B6=0),"",MIN(1,$C6/$B6)) -> 0.38333333
A7: Japan trip | B7: 2400 | C7: 600 | D7: 46568 | E7: =IF(OR($A7="",$D7=""),"",MAX(0,(YEAR($D7)-YEAR(TODAY()))*12+MONTH($D7)-MONTH(TODAY()))) -> 10 | F7: =IF(OR($A7="",$B7="",$D7=""),"",IF($E7=0,MAX(0,$B7-$C7),ROUND(MAX(0,$B7-$C7)/$E7,2))) -> 180 | G7: =IF(OR($A7="",$B7="",$B7=0),"",MIN(1,$C7/$B7)) -> 0.25
E8: =IF(OR($A8="",$D8=""),"",MAX(0,(YEAR($D8)-YEAR(TODAY()))*12+MONTH($D8)-MONTH(TODAY()))) | F8: =IF(OR($A8="",$B8="",$D8=""),"",IF($E8=0,MAX(0,$B8-$C8),ROUND(MAX(0,$B8-$C8)/$E8,2))) | G8: =IF(OR($A8="",$B8="",$B8=0),"",MIN(1,$C8/$B8))
E9: =IF(OR($A9="",$D9=""),"",MAX(0,(YEAR($D9)-YEAR(TODAY()))*12+MONTH($D9)-MONTH(TODAY()))) | F9: =IF(OR($A9="",$B9="",$D9=""),"",IF($E9=0,MAX(0,$B9-$C9),ROUND(MAX(0,$B9-$C9)/$E9,2))) | G9: =IF(OR($A9="",$B9="",$B9=0),"",MIN(1,$C9/$B9))
E10: =IF(OR($A10="",$D10=""),"",MAX(0,(YEAR($D10)-YEAR(TODAY()))*12+MONTH($D10)-MONTH(TODAY()))) | F10: =IF(OR($A10="",$B10="",$D10=""),"",IF($E10=0,MAX(0,$B10-$C10),ROUND(MAX(0,$B10-$C10)/$E10,2))) | G10: =IF(OR($A10="",$B10="",$B10=0),"",MIN(1,$C10/$B10))
E11: =IF(OR($A11="",$D11=""),"",MAX(0,(YEAR($D11)-YEAR(TODAY()))*12+MONTH($D11)-MONTH(TODAY()))) | F11: =IF(OR($A11="",$B11="",$D11=""),"",IF($E11=0,MAX(0,$B11-$C11),ROUND(MAX(0,$B11-$C11)/$E11,2))) | G11: =IF(OR($A11="",$B11="",$B11=0),"",MIN(1,$C11/$B11))
E12: =IF(OR($A12="",$D12=""),"",MAX(0,(YEAR($D12)-YEAR(TODAY()))*12+MONTH($D12)-MONTH(TODAY()))) | F12: =IF(OR($A12="",$B12="",$D12=""),"",IF($E12=0,MAX(0,$B12-$C12),ROUND(MAX(0,$B12-$C12)/$E12,2))) | G12: =IF(OR($A12="",$B12="",$B12=0),"",MIN(1,$C12/$B12))
E13: =IF(OR($A13="",$D13=""),"",MAX(0,(YEAR($D13)-YEAR(TODAY()))*12+MONTH($D13)-MONTH(TODAY()))) | F13: =IF(OR($A13="",$B13="",$D13=""),"",IF($E13=0,MAX(0,$B13-$C13),ROUND(MAX(0,$B13-$C13)/$E13,2))) | G13: =IF(OR($A13="",$B13="",$B13=0),"",MIN(1,$C13/$B13))
E14: =IF(OR($A14="",$D14=""),"",MAX(0,(YEAR($D14)-YEAR(TODAY()))*12+MONTH($D14)-MONTH(TODAY()))) | F14: =IF(OR($A14="",$B14="",$D14=""),"",IF($E14=0,MAX(0,$B14-$C14),ROUND(MAX(0,$B14-$C14)/$E14,2))) | G14: =IF(OR($A14="",$B14="",$B14=0),"",MIN(1,$C14/$B14))
E15: =IF(OR($A15="",$D15=""),"",MAX(0,(YEAR($D15)-YEAR(TODAY()))*12+MONTH($D15)-MONTH(TODAY()))) | F15: =IF(OR($A15="",$B15="",$D15=""),"",IF($E15=0,MAX(0,$B15-$C15),ROUND(MAX(0,$B15-$C15)/$E15,2))) | G15: =IF(OR($A15="",$B15="",$B15=0),"",MIN(1,$C15/$B15))
A17: Total | B17: =SUM(B6:B15) -> 5400 | C17: =SUM(C6:C15) -> 1750
A19: Tip: pair this with the “Savings & investing” budget category so goal money is planned, not leftover.
