Workbook

Sheet Start Here
A1: Small Business Bookkeeping Tracker
A2: Every sale, every expense, and your real profit — in one tidy file.
B4: Welcome!
B5: Built for sellers on Gumroad, Etsy, Shopify or anywhere else: log sales and expenses as they happen, and the dashboard shows monthly profit, fees, and your best-selling products automatically.
B8: 1. List your products
C9: On the Products tab, add what you sell. Product names become a dropdown on the Income tab.
B11: 2. Log every sale
C12: On Income: date, product, platform, gross amount, and platform fees. Net is calculated for you.
B14: 3. Log every expense
C15: On Expenses: date, category (dropdown), description, amount. Software, ads, supplies — all of it.
B17: 4. Read the Dashboard
C18: Revenue, expenses, profit and margin for the year, month by month, by platform, and by product.
B20: Color guide
C21: Light yellow cells = yours to fill in or change
C22: Grey / white cells = calculated automatically — no need to touch them
B24: Note: the file includes a few example rows so you can see how it works — delete them and add your own.
B25: Works in Microsoft Excel (2016 or newer) and Google Sheets (upload to Drive, then Open with Google Sheets).
B26: This is a bookkeeping aid, not tax or accounting advice.

Sheet Products
A1: Products
A2: What you sell. Names here become the dropdown on the Income tab.
A5: Product / service | B5: Typical price | C5: Notes
A6: Budget Template | B6: 12 | C6: Sold on Gumroad + Etsy
A7: Invoice Template Pack | B7: 14

Sheet Income
A1: Income
A2: One row per sale. Net = gross minus fees, calculated for you.
A4: Type in every column except Net. Pick Product and Platform from the dropdowns.
A5: Date | B5: Product / service | C5: Platform | D5: Gross | E5: Fees | F5: Net | G5: Notes
A6: 46217 | B6: Budget Template | C6: Gumroad | D6: 12 | E6: 1.55 | F6: =IF($D6="","",ROUND($D6-IF($E6="",0,$E6),2)) -> 10.45 | G6: First sale!
A7: 46231 | B7: Invoice Template Pack | C7: Gumroad | D7: 14 | E7: 1.77 | F7: =IF($D7="","",ROUND($D7-IF($E7="",0,$E7),2)) -> 12.23
A8: 46236 | B8: Budget Template | C8: Etsy | D8: 12 | E8: 2.72 | F8: =IF($D8="","",ROUND($D8-IF($E8="",0,$E8),2)) -> 9.28 | G8: Etsy listing
A9: 46243 | B9: Invoice Template Pack | C9: Direct | D9: 14 | F9: =IF($D9="","",ROUND($D9-IF($E9="",0,$E9),2)) -> 14 | G9: Sold via email
F10: =IF($D10="","",ROUND($D10-IF($E10="",0,$E10),2))
F11: =IF($D11="","",ROUND($D11-IF($E11="",0,$E11),2))
F12: =IF($D12="","",ROUND($D12-IF($E12="",0,$E12),2))
F13: =IF($D13="","",ROUND($D13-IF($E13="",0,$E13),2))
F14: =IF($D14="","",ROUND($D14-IF($E14="",0,$E14),2))
F15: =IF($D15="","",ROUND($D15-IF($E15="",0,$E15),2))
F16: =IF($D16="","",ROUND($D16-IF($E16="",0,$E16),2))
F17: =IF($D17="","",ROUND($D17-IF($E17="",0,$E17),2))
F18: =IF($D18="","",ROUND($D18-IF($E18="",0,$E18),2))
F19: =IF($D19="","",ROUND($D19-IF($E19="",0,$E19),2))
F20: =IF($D20="","",ROUND($D20-IF($E20="",0,$E20),2))
F21: =IF($D21="","",ROUND($D21-IF($E21="",0,$E21),2))
... F305: =IF($D305="","",ROUND($D305-IF($E305="",0,$E305),2))

Sheet Expenses
A1: Expenses
A2: One row per business expense. The Dashboard reads this table.
A4: Every cell in this table is yours to type in. Pick the Category from the dropdown.
A5: Date | B5: Category | C5: Description | D5: Amount
A6: 46213 | B6: Software & tools | C6: Canva Pro (monthly) | D6: 12.99
A7: 46239 | B7: Marketing & ads | C7: Pinterest ads test | D7: 25

Sheet Dashboard
A1: Dashboard
A2: Profit at a glance. Everything updates automatically from Income and Expenses.
B4: Year | C4: 2026
B6: REVENUE (NET) | D6: EXPENSES | G6: PROFIT | J6: PROFIT MARGIN
B7: =SUMIFS(Income!$F$6:$F$305,Income!$A$6:$A$305,">="&DATE($C$4,1,1),Income!$A$6:$A$305,"<"&DATE($C$4+1,1,1)) -> 45.96 | D7: =SUMIFS(Expenses!$D$6:$D$305,Expenses!$A$6:$A$305,">="&DATE($C$4,1,1),Expenses!$A$6:$A$305,"<"&DATE($C$4+1,1,1)) -> 37.99 | G7: =B7-D7 -> 7.97 | J7: =IF($B$7=0,"",($B$7-$D$7)/$B$7) -> 0.17341166
B10: Month by month | G10: By platform | J10: By product
A11: # | B11: Month | C11: Revenue | D11: Expenses | E11: Profit | G11: Platform | H11: Net revenue | J11: Product | K11: Net revenue
A12: 1 | B12: January | C12: =SUMIFS(Income!$F$6:$F$305,Income!$A$6:$A$305,">="&DATE($C$4,$A12,1),Income!$A$6:$A$305,"<"&DATE($C$4,$A12+1,1)) -> 0 | D12: =SUMIFS(Expenses!$D$6:$D$305,Expenses!$A$6:$A$305,">="&DATE($C$4,$A12,1),Expenses!$A$6:$A$305,"<"&DATE($C$4,$A12+1,1)) -> 0 | E12: =C12-D12 -> 0 | G12: Gumroad | H12: =SUMIFS(Income!$F$6:$F$305,Income!$C$6:$C$305,"Gumroad",Income!$A$6:$A$305,">="&DATE($C$4,1,1),Income!$A$6:$A$305,"<"&DATE($C$4+1,1,1)) -> 22.68 | J12: =IF(Products!A6="","",Products!A6) -> Budget Template | K12: =IF($J12="","",SUMIFS(Income!$F$6:$F$305,Income!$B$6:$B$305,$J12,Income!$A$6:$A$305,">="&DATE($C$4,1,1),Income!$A$6:$A$305,"<"&DATE($C$4+1,1,1))) -> 19.73
A13: 2 | B13: February | C13: =SUMIFS(Income!$F$6:$F$305,Income!$A$6:$A$305,">="&DATE($C$4,$A13,1),Income!$A$6:$A$305,"<"&DATE($C$4,$A13+1,1)) -> 0 | D13: =SUMIFS(Expenses!$D$6:$D$305,Expenses!$A$6:$A$305,">="&DATE($C$4,$A13,1),Expenses!$A$6:$A$305,"<"&DATE($C$4,$A13+1,1)) -> 0 | E13: =C13-D13 -> 0 | G13: Etsy | H13: =SUMIFS(Income!$F$6:$F$305,Income!$C$6:$C$305,"Etsy",Income!$A$6:$A$305,">="&DATE($C$4,1,1),Income!$A$6:$A$305,"<"&DATE($C$4+1,1,1)) -> 9.28 | J13: =IF(Products!A7="","",Products!A7) -> Invoice Template Pack | K13: =IF($J13="","",SUMIFS(Income!$F$6:$F$305,Income!$B$6:$B$305,$J13,Income!$A$6:$A$305,">="&DATE($C$4,1,1),Income!$A$6:$A$305,"<"&DATE($C$4+1,1,1))) -> 26.23
A14: 3 | B14: March | C14: =SUMIFS(Income!$F$6:$F$305,Income!$A$6:$A$305,">="&DATE($C$4,$A14,1),Income!$A$6:$A$305,"<"&DATE($C$4,$A14+1,1)) -> 0 | D14: =SUMIFS(Expenses!$D$6:$D$305,Expenses!$A$6:$A$305,">="&DATE($C$4,$A14,1),Expenses!$A$6:$A$305,"<"&DATE($C$4,$A14+1,1)) -> 0 | E14: =C14-D14 -> 0 | G14: Shopify | H14: =SUMIFS(Income!$F$6:$F$305,Income!$C$6:$C$305,"Shopify",Income!$A$6:$A$305,">="&DATE($C$4,1,1),Income!$A$6:$A$305,"<"&DATE($C$4+1,1,1)) -> 0 | J14: =IF(Products!A8="","",Products!A8) | K14: =IF($J14="","",SUMIFS(Income!$F$6:$F$305,Income!$B$6:$B$305,$J14,Income!$A$6:$A$305,">="&DATE($C$4,1,1),Income!$A$6:$A$305,"<"&DATE($C$4+1,1,1)))
A15: 4 | B15: April | C15: =SUMIFS(Income!$F$6:$F$305,Income!$A$6:$A$305,">="&DATE($C$4,$A15,1),Income!$A$6:$A$305,"<"&DATE($C$4,$A15+1,1)) -> 0 | D15: =SUMIFS(Expenses!$D$6:$D$305,Expenses!$A$6:$A$305,">="&DATE($C$4,$A15,1),Expenses!$A$6:$A$305,"<"&DATE($C$4,$A15+1,1)) -> 0 | E15: =C15-D15 -> 0 | G15: Direct | H15: =SUMIFS(Income!$F$6:$F$305,Income!$C$6:$C$305,"Direct",Income!$A$6:$A$305,">="&DATE($C$4,1,1),Income!$A$6:$A$305,"<"&DATE($C$4+1,1,1)) -> 14 | J15: =IF(Products!A9="","",Products!A9) | K15: =IF($J15="","",SUMIFS(Income!$F$6:$F$305,Income!$B$6:$B$305,$J15,Income!$A$6:$A$305,">="&DATE($C$4,1,1),Income!$A$6:$A$305,"<"&DATE($C$4+1,1,1)))
A16: 5 | B16: May | C16: =SUMIFS(Income!$F$6:$F$305,Income!$A$6:$A$305,">="&DATE($C$4,$A16,1),Income!$A$6:$A$305,"<"&DATE($C$4,$A16+1,1)) -> 0 | D16: =SUMIFS(Expenses!$D$6:$D$305,Expenses!$A$6:$A$305,">="&DATE($C$4,$A16,1),Expenses!$A$6:$A$305,"<"&DATE($C$4,$A16+1,1)) -> 0 | E16: =C16-D16 -> 0 | G16: Other | H16: =SUMIFS(Income!$F$6:$F$305,Income!$C$6:$C$305,"Other",Income!$A$6:$A$305,">="&DATE($C$4,1,1),Income!$A$6:$A$305,"<"&DATE($C$4+1,1,1)) -> 0 | J16: =IF(Products!A10="","",Products!A10) | K16: =IF($J16="","",SUMIFS(Income!$F$6:$F$305,Income!$B$6:$B$305,$J16,Income!$A$6:$A$305,">="&DATE($C$4,1,1),Income!$A$6:$A$305,"<"&DATE($C$4+1,1,1)))
A17: 6 | B17: June | C17: =SUMIFS(Income!$F$6:$F$305,Income!$A$6:$A$305,">="&DATE($C$4,$A17,1),Income!$A$6:$A$305,"<"&DATE($C$4,$A17+1,1)) -> 0 | D17: =SUMIFS(Expenses!$D$6:$D$305,Expenses!$A$6:$A$305,">="&DATE($C$4,$A17,1),Expenses!$A$6:$A$305,"<"&DATE($C$4,$A17+1,1)) -> 0 | E17: =C17-D17 -> 0 | J17: =IF(Products!A11="","",Products!A11) | K17: =IF($J17="","",SUMIFS(Income!$F$6:$F$305,Income!$B$6:$B$305,$J17,Income!$A$6:$A$305,">="&DATE($C$4,1,1),Income!$A$6:$A$305,"<"&DATE($C$4+1,1,1)))
A18: 7 | B18: July | C18: =SUMIFS(Income!$F$6:$F$305,Income!$A$6:$A$305,">="&DATE($C$4,$A18,1),Income!$A$6:$A$305,"<"&DATE($C$4,$A18+1,1)) -> 22.68 | D18: =SUMIFS(Expenses!$D$6:$D$305,Expenses!$A$6:$A$305,">="&DATE($C$4,$A18,1),Expenses!$A$6:$A$305,"<"&DATE($C$4,$A18+1,1)) -> 12.99 | E18: =C18-D18 -> 9.69 | J18: =IF(Products!A12="","",Products!A12) | K18: =IF($J18="","",SUMIFS(Income!$F$6:$F$305,Income!$B$6:$B$305,$J18,Income!$A$6:$A$305,">="&DATE($C$4,1,1),Income!$A$6:$A$305,"<"&DATE($C$4+1,1,1)))
A19: 8 | B19: August | C19: =SUMIFS(Income!$F$6:$F$305,Income!$A$6:$A$305,">="&DATE($C$4,$A19,1),Income!$A$6:$A$305,"<"&DATE($C$4,$A19+1,1)) -> 23.28 | D19: =SUMIFS(Expenses!$D$6:$D$305,Expenses!$A$6:$A$305,">="&DATE($C$4,$A19,1),Expenses!$A$6:$A$305,"<"&DATE($C$4,$A19+1,1)) -> 25 | E19: =C19-D19 -> -1.72 | J19: =IF(Products!A13="","",Products!A13) | K19: =IF($J19="","",SUMIFS(Income!$F$6:$F$305,Income!$B$6:$B$305,$J19,Income!$A$6:$A$305,">="&DATE($C$4,1,1),Income!$A$6:$A$305,"<"&DATE($C$4+1,1,1)))
A20: 9 | B20: September | C20: =SUMIFS(Income!$F$6:$F$305,Income!$A$6:$A$305,">="&DATE($C$4,$A20,1),Income!$A$6:$A$305,"<"&DATE($C$4,$A20+1,1)) -> 0 | D20: =SUMIFS(Expenses!$D$6:$D$305,Expenses!$A$6:$A$305,">="&DATE($C$4,$A20,1),Expenses!$A$6:$A$305,"<"&DATE($C$4,$A20+1,1)) -> 0 | E20: =C20-D20 -> 0 | J20: =IF(Products!A14="","",Products!A14) | K20: =IF($J20="","",SUMIFS(Income!$F$6:$F$305,Income!$B$6:$B$305,$J20,Income!$A$6:$A$305,">="&DATE($C$4,1,1),Income!$A$6:$A$305,"<"&DATE($C$4+1,1,1)))
A21: 10 | B21: October | C21: =SUMIFS(Income!$F$6:$F$305,Income!$A$6:$A$305,">="&DATE($C$4,$A21,1),Income!$A$6:$A$305,"<"&DATE($C$4,$A21+1,1)) -> 0 | D21: =SUMIFS(Expenses!$D$6:$D$305,Expenses!$A$6:$A$305,">="&DATE($C$4,$A21,1),Expenses!$A$6:$A$305,"<"&DATE($C$4,$A21+1,1)) -> 0 | E21: =C21-D21 -> 0 | J21: =IF(Products!A15="","",Products!A15) | K21: =IF($J21="","",SUMIFS(Income!$F$6:$F$305,Income!$B$6:$B$305,$J21,Income!$A$6:$A$305,">="&DATE($C$4,1,1),Income!$A$6:$A$305,"<"&DATE($C$4+1,1,1)))
A22: 11 | B22: November | C22: =SUMIFS(Income!$F$6:$F$305,Income!$A$6:$A$305,">="&DATE($C$4,$A22,1),Income!$A$6:$A$305,"<"&DATE($C$4,$A22+1,1)) -> 0 | D22: =SUMIFS(Expenses!$D$6:$D$305,Expenses!$A$6:$A$305,">="&DATE($C$4,$A22,1),Expenses!$A$6:$A$305,"<"&DATE($C$4,$A22+1,1)) -> 0 | E22: =C22-D22 -> 0 | J22: =IF(Products!A16="","",Products!A16) | K22: =IF($J22="","",SUMIFS(Income!$F$6:$F$305,Income!$B$6:$B$305,$J22,Income!$A$6:$A$305,">="&DATE($C$4,1,1),Income!$A$6:$A$305,"<"&DATE($C$4+1,1,1)))
A23: 12 | B23: December | C23: =SUMIFS(Income!$F$6:$F$305,Income!$A$6:$A$305,">="&DATE($C$4,$A23,1),Income!$A$6:$A$305,"<"&DATE($C$4,$A23+1,1)) -> 0 | D23: =SUMIFS(Expenses!$D$6:$D$305,Expenses!$A$6:$A$305,">="&DATE($C$4,$A23,1),Expenses!$A$6:$A$305,"<"&DATE($C$4,$A23+1,1)) -> 0 | E23: =C23-D23 -> 0 | J23: =IF(Products!A17="","",Products!A17) | K23: =IF($J23="","",SUMIFS(Income!$F$6:$F$305,Income!$B$6:$B$305,$J23,Income!$A$6:$A$305,">="&DATE($C$4,1,1),Income!$A$6:$A$305,"<"&DATE($C$4+1,1,1)))
J24: =IF(Products!A18="","",Products!A18) | K24: =IF($J24="","",SUMIFS(Income!$F$6:$F$305,Income!$B$6:$B$305,$J24,Income!$A$6:$A$305,">="&DATE($C$4,1,1),Income!$A$6:$A$305,"<"&DATE($C$4+1,1,1)))
J25: =IF(Products!A19="","",Products!A19) | K25: =IF($J25="","",SUMIFS(Income!$F$6:$F$305,Income!$B$6:$B$305,$J25,Income!$A$6:$A$305,">="&DATE($C$4,1,1),Income!$A$6:$A$305,"<"&DATE($C$4+1,1,1)))
J26: =IF(Products!A20="","",Products!A20) | K26: =IF($J26="","",SUMIFS(Income!$F$6:$F$305,Income!$B$6:$B$305,$J26,Income!$A$6:$A$305,">="&DATE($C$4,1,1),Income!$A$6:$A$305,"<"&DATE($C$4+1,1,1)))
J27: =IF(Products!A21="","",Products!A21) | K27: =IF($J27="","",SUMIFS(Income!$F$6:$F$305,Income!$B$6:$B$305,$J27,Income!$A$6:$A$305,">="&DATE($C$4,1,1),Income!$A$6:$A$305,"<"&DATE($C$4+1,1,1)))
J28: =IF(Products!A22="","",Products!A22) | K28: =IF($J28="","",SUMIFS(Income!$F$6:$F$305,Income!$B$6:$B$305,$J28,Income!$A$6:$A$305,">="&DATE($C$4,1,1),Income!$A$6:$A$305,"<"&DATE($C$4+1,1,1)))
J29: =IF(Products!A23="","",Products!A23) | K29: =IF($J29="","",SUMIFS(Income!$F$6:$F$305,Income!$B$6:$B$305,$J29,Income!$A$6:$A$305,">="&DATE($C$4,1,1),Income!$A$6:$A$305,"<"&DATE($C$4+1,1,1)))
J30: =IF(Products!A24="","",Products!A24) | K30: =IF($J30="","",SUMIFS(Income!$F$6:$F$305,Income!$B$6:$B$305,$J30,Income!$A$6:$A$305,">="&DATE($C$4,1,1),Income!$A$6:$A$305,"<"&DATE($C$4+1,1,1)))
J31: =IF(Products!A25="","",Products!A25) | K31: =IF($J31="","",SUMIFS(Income!$F$6:$F$305,Income!$B$6:$B$305,$J31,Income!$A$6:$A$305,">="&DATE($C$4,1,1),Income!$A$6:$A$305,"<"&DATE($C$4+1,1,1)))
